{"version": 1, "provider_id": "pexels", "query": "oversleep", "ts": 1779456795, "results": [{"provider_id": "pexels", "thumbnail_url": "https://images.pexels.com/photos/11790890/pexels-photo-11790890.jpeg?auto=compress&cs=tinysrgb&h=350", "full_url": "https://images.pexels.com/photos/11790890/pexels-photo-11790890.jpeg?auto=compress&cs=tinysrgb&dpr=2&h=650&w=940", "extension": "jpg", "source_page_url": "https://www.pexels.com/photo/couple-in-bed-with-alarm-clock-11790890/", "author_name": "Rhema Emeka-Chiemenem", "author_url": "https://www.pexels.com/@rhema-emeka-chiemenem-213163182", "license_name": "Pexels License", "license_url": "https://www.pexels.com/license/", "fallback_full_urls": []}, {"provider_id": "pexels", "thumbnail_url": "https://images.pexels.com/photos/20672938/pexels-photo-20672938.jpeg?auto=compress&cs=tinysrgb&h=350", "full_url": "https://images.pexels.com/photos/20672938/pexels-photo-20672938.jpeg?auto=compress&cs=tinysrgb&dpr=2&h=650&w=940", "extension": "jpg", "source_page_url": "https://www.pexels.com/photo/worried-man-sitting-at-table-in-kitchen-20672938/", "author_name": "Lucas Andrade", "author_url": "https://www.pexels.com/@lucasandrade", "license_name": "Pexels License", "license_url": "https://www.pexels.com/license/", "fallback_full_urls": []}, {"provider_id": "pexels", "thumbnail_url": "https://images.pexels.com/photos/8264237/pexels-photo-8264237.jpeg?auto=compress&cs=tinysrgb&h=350", "full_url": "https://images.pexels.com/photos/8264237/pexels-photo-8264237.jpeg?auto=compress&cs=tinysrgb&dpr=2&h=650&w=940", "extension": "jpg", "source_page_url": "https://www.pexels.com/photo/a-woman-in-white-long-sleeves-yawning-8264237/", "author_name": "Ron Lach", "author_url": "https://www.pexels.com/@ron-lach", "license_name": "Pexels License", "license_url": "https://www.pexels.com/license/", "fallback_full_urls": []}, {"provider_id": "pexels", "thumbnail_url": "https://images.pexels.com/photos/8406962/pexels-photo-8406962.jpeg?auto=compress&cs=tinysrgb&h=350", "full_url": "https://images.pexels.com/photos/8406962/pexels-photo-8406962.jpeg?auto=compress&cs=tinysrgb&dpr=2&h=650&w=940", "extension": "jpg", "source_page_url": "https://www.pexels.com/photo/alarm-clock-and-pencils-on-white-background-8406962/", "author_name": "Tara Winstead", "author_url": "https://www.pexels.com/@tara-winstead", "license_name": "Pexels License", "license_url": "https://www.pexels.com/license/", "fallback_full_urls": []}, {"provider_id": "pexels", "thumbnail_url": "https://images.pexels.com/photos/8416438/pexels-photo-8416438.jpeg?auto=compress&cs=tinysrgb&h=350", "full_url": "https://images.pexels.com/photos/8416438/pexels-photo-8416438.jpeg?auto=compress&cs=tinysrgb&dpr=2&h=650&w=940", "extension": "jpg", "source_page_url": "https://www.pexels.com/photo/a-woman-in-light-blue-long-sleeves-with-pillow-on-her-head-8416438/", "author_name": "SHVETS production", "author_url": "https://www.pexels.com/@shvets-production", "license_name": "Pexels License", "license_url": "https://www.pexels.com/license/", "fallback_full_urls": []}, {"provider_id": "pexels", "thumbnail_url": "https://images.pexels.com/photos/6753371/pexels-photo-6753371.jpeg?auto=compress&cs=tinysrgb&h=350", "full_url": "https://images.pexels.com/photos/6753371/pexels-photo-6753371.jpeg?auto=compress&cs=tinysrgb&dpr=2&h=650&w=940", "extension": "jpg", "source_page_url": "https://www.pexels.com/photo/a-woman-yawning-while-lying-on-the-bed-6753371/", "author_name": "cottonbro studio", "author_url": "https://www.pexels.com/@cottonbro", "license_name": "Pexels License", "license_url": "https://www.pexels.com/license/", "fallback_full_urls": []}, {"provider_id": "pexels", "thumbnail_url": "https://images.pexels.com/photos/8416307/pexels-photo-8416307.jpeg?auto=compress&cs=tinysrgb&h=350", "full_url": "https://images.pexels.com/photos/8416307/pexels-photo-8416307.jpeg?auto=compress&cs=tinysrgb&dpr=2&h=650&w=940", "extension": "jpg", "source_page_url": "https://www.pexels.com/photo/a-woman-looking-at-the-camera-8416307/", "author_name": "SHVETS production", "author_url": "https://www.pexels.com/@shvets-production", "license_name": "Pexels License", "license_url": "https://www.pexels.com/license/", "fallback_full_urls": []}, {"provider_id": "pexels", "thumbnail_url": "https://images.pexels.com/photos/5331094/pexels-photo-5331094.jpeg?auto=compress&cs=tinysrgb&h=350", "full_url": "https://images.pexels.com/photos/5331094/pexels-photo-5331094.jpeg?auto=compress&cs=tinysrgb&dpr=2&h=650&w=940", "extension": "jpg", "source_page_url": "https://www.pexels.com/photo/sleepy-woman-lying-on-bed-with-alarm-on-smartphone-5331094/", "author_name": "Monstera Production", "author_url": "https://www.pexels.com/@gabby-k", "license_name": "Pexels License", "license_url": "https://www.pexels.com/license/", "fallback_full_urls": []}, {"provider_id": "pexels", "thumbnail_url": "https://images.pexels.com/photos/11344545/pexels-photo-11344545.jpeg?auto=compress&cs=tinysrgb&h=350", "full_url": "https://images.pexels.com/photos/11344545/pexels-photo-11344545.jpeg?auto=compress&cs=tinysrgb&dpr=2&h=650&w=940", "extension": "jpg", "source_page_url": "https://www.pexels.com/photo/a-black-alarm-clock-11344545/", "author_name": "Towfiqu barbhuiya", "author_url": "https://www.pexels.com/@towfiqu-barbhuiya-3440682", "license_name": "Pexels License", "license_url": "https://www.pexels.com/license/", "fallback_full_urls": []}, {"provider_id": "pexels", "thumbnail_url": "https://images.pexels.com/photos/4752713/pexels-photo-4752713.jpeg?auto=compress&cs=tinysrgb&h=350", "full_url": "https://images.pexels.com/photos/4752713/pexels-photo-4752713.jpeg?auto=compress&cs=tinysrgb&dpr=2&h=650&w=940", "extension": "jpg", "source_page_url": "https://www.pexels.com/photo/sleepy-woman-yawning-on-bed-4752713/", "author_name": "Vika Glitter", "author_url": "https://www.pexels.com/@vika-glitter-392079", "license_name": "Pexels License", "license_url": "https://www.pexels.com/license/", "fallback_full_urls": []}, {"provider_id": "pexels", "thumbnail_url": "https://images.pexels.com/photos/9615248/pexels-photo-9615248.jpeg?auto=compress&cs=tinysrgb&h=350", "full_url": "https://images.pexels.com/photos/9615248/pexels-photo-9615248.jpeg?auto=compress&cs=tinysrgb&dpr=2&h=650&w=940", "extension": "jpg", "source_page_url": "https://www.pexels.com/photo/woman-lying-on-bed-covered-with-black-blanket-9615248/", "author_name": "Ron Lach", "author_url": "https://www.pexels.com/@ron-lach", "license_name": "Pexels License", "license_url": "https://www.pexels.com/license/", "fallback_full_urls": []}, {"provider_id": "pexels", "thumbnail_url": "https://images.pexels.com/photos/18471289/pexels-photo-18471289.jpeg?auto=compress&cs=tinysrgb&h=350", "full_url": "https://images.pexels.com/photos/18471289/pexels-photo-18471289.jpeg?auto=compress&cs=tinysrgb&dpr=2&h=650&w=940", "extension": "jpg", "source_page_url": "https://www.pexels.com/photo/person-sleeping-in-bed-with-a-book-on-her-face-18471289/", "author_name": "Deniz Kyzyltoprak", "author_url": "https://www.pexels.com/@deniz-kyzyltoprak-166600332", "license_name": "Pexels License", "license_url": "https://www.pexels.com/license/", "fallback_full_urls": []}, {"provider_id": "pexels", "thumbnail_url": "https://images.pexels.com/photos/7445321/pexels-photo-7445321.jpeg?auto=compress&cs=tinysrgb&h=350", "full_url": "https://images.pexels.com/photos/7445321/pexels-photo-7445321.jpeg?auto=compress&cs=tinysrgb&dpr=2&h=650&w=940", "extension": "jpg", "source_page_url": "https://www.pexels.com/photo/a-man-lying-on-the-bed-7445321/", "author_name": "KATRIN  BOLOVTSOVA", "author_url": "https://www.pexels.com/@ekaterina-bolovtsova", "license_name": "Pexels License", "license_url": "https://www.pexels.com/license/", "fallback_full_urls": []}, {"provider_id": "pexels", "thumbnail_url": "https://images.pexels.com/photos/5712080/pexels-photo-5712080.jpeg?auto=compress&cs=tinysrgb&h=350", "full_url": "https://images.pexels.com/photos/5712080/pexels-photo-5712080.jpeg?auto=compress&cs=tinysrgb&dpr=2&h=650&w=940", "extension": "jpg", "source_page_url": "https://www.pexels.com/photo/an-exhausted-man-lying-on-bed-rubbing-his-eyes-5712080/", "author_name": "Arina Krasnikova", "author_url": "https://www.pexels.com/@arina-krasnikova", "license_name": "Pexels License", "license_url": "https://www.pexels.com/license/", "fallback_full_urls": []}, {"provider_id": "pexels", "thumbnail_url": "https://images.pexels.com/photos/9788264/pexels-photo-9788264.jpeg?auto=compress&cs=tinysrgb&h=350", "full_url": "https://images.pexels.com/photos/9788264/pexels-photo-9788264.jpeg?auto=compress&cs=tinysrgb&dpr=2&h=650&w=940", "extension": "jpg", "source_page_url": "https://www.pexels.com/photo/a-woman-sleeping-in-the-bed-9788264/", "author_name": "Marcus Aurelius", "author_url": "https://www.pexels.com/@marcus-aurelius", "license_name": "Pexels License", "license_url": "https://www.pexels.com/license/", "fallback_full_urls": []}, {"provider_id": "pexels", "thumbnail_url": "https://images.pexels.com/photos/7445336/pexels-photo-7445336.jpeg?auto=compress&cs=tinysrgb&h=350", "full_url": "https://images.pexels.com/photos/7445336/pexels-photo-7445336.jpeg?auto=compress&cs=tinysrgb&dpr=2&h=650&w=940", "extension": "jpg", "source_page_url": "https://www.pexels.com/photo/man-sleeping-on-the-bed-on-white-background-7445336/", "author_name": "KATRIN  BOLOVTSOVA", "author_url": "https://www.pexels.com/@ekaterina-bolovtsova", "license_name": "Pexels License", "license_url": "https://www.pexels.com/license/", "fallback_full_urls": []}, {"provider_id": "pexels", "thumbnail_url": "https://images.pexels.com/photos/9787616/pexels-photo-9787616.jpeg?auto=compress&cs=tinysrgb&h=350", "full_url": "https://images.pexels.com/photos/9787616/pexels-photo-9787616.jpeg?auto=compress&cs=tinysrgb&dpr=2&h=650&w=940", "extension": "jpg", "source_page_url": "https://www.pexels.com/photo/a-woman-with-eye-mask-sleeping-in-the-bed-9787616/", "author_name": "Marcus Aurelius", "author_url": "https://www.pexels.com/@marcus-aurelius", "license_name": "Pexels License", "license_url": "https://www.pexels.com/license/", "fallback_full_urls": []}, {"provider_id": "pexels", "thumbnail_url": "https://images.pexels.com/photos/4584491/pexels-photo-4584491.jpeg?auto=compress&cs=tinysrgb&h=350", "full_url": "https://images.pexels.com/photos/4584491/pexels-photo-4584491.jpeg?auto=compress&cs=tinysrgb&dpr=2&h=650&w=940", "extension": "jpg", "source_page_url": "https://www.pexels.com/photo/a-sleepy-man-in-yellow-crew-neck-t-shirt-4584491/", "author_name": "Ketut Subiyanto", "author_url": "https://www.pexels.com/@ketut-subiyanto", "license_name": "Pexels License", "license_url": "https://www.pexels.com/license/", "fallback_full_urls": []}, {"provider_id": "pexels", "thumbnail_url": "https://images.pexels.com/photos/7556603/pexels-photo-7556603.jpeg?auto=compress&cs=tinysrgb&h=350", "full_url": "https://images.pexels.com/photos/7556603/pexels-photo-7556603.jpeg?auto=compress&cs=tinysrgb&dpr=2&h=650&w=940", "extension": "jpg", "source_page_url": "https://www.pexels.com/photo/woman-in-gray-shirt-stretching-in-bed-7556603/", "author_name": "Kampus Production", "author_url": "https://www.pexels.com/@kampus", "license_name": "Pexels License", "license_url": "https://www.pexels.com/license/", "fallback_full_urls": []}, {"provider_id": "pexels", "thumbnail_url": "https://images.pexels.com/photos/4080038/pexels-photo-4080038.jpeg?auto=compress&cs=tinysrgb&h=350", "full_url": "https://images.pexels.com/photos/4080038/pexels-photo-4080038.jpeg?auto=compress&cs=tinysrgb&dpr=2&h=650&w=940", "extension": "jpg", "source_page_url": "https://www.pexels.com/photo/woman-covered-in-white-blanket-lying-on-bed-4080038/", "author_name": "Elvira Gibadullina", "author_url": "https://www.pexels.com/@elvira-gibadullina-2457991", "license_name": "Pexels License", "license_url": "https://www.pexels.com/license/", "fallback_full_urls": []}, {"provider_id": "pexels", "thumbnail_url": "https://images.pexels.com/photos/2230792/pexels-photo-2230792.jpeg?auto=compress&cs=tinysrgb&h=350", "full_url": "https://images.pexels.com/photos/2230792/pexels-photo-2230792.jpeg?auto=compress&cs=tinysrgb&dpr=2&h=650&w=940", "extension": "jpg", "source_page_url": "https://www.pexels.com/photo/woman-lying-on-bed-2230792/", "author_name": "Luana  Bento", "author_url": "https://www.pexels.com/@luana", "license_name": "Pexels License", "license_url": "https://www.pexels.com/license/", "fallback_full_urls": []}, {"provider_id": "pexels", "thumbnail_url": "https://images.pexels.com/photos/296817/pexels-photo-296817.jpeg?auto=compress&cs=tinysrgb&h=350", "full_url": "https://images.pexels.com/photos/296817/pexels-photo-296817.jpeg?auto=compress&cs=tinysrgb&dpr=2&h=650&w=940", "extension": "jpg", "source_page_url": "https://www.pexels.com/photo/man-wearing-green-printed-crew-neck-shirt-while-sleeping-296817/", "author_name": "John-Mark Smith", "author_url": "https://www.pexels.com/@jmark", "license_name": "Pexels License", "license_url": "https://www.pexels.com/license/", "fallback_full_urls": []}, {"provider_id": "pexels", "thumbnail_url": "https://images.pexels.com/photos/10895246/pexels-photo-10895246.jpeg?auto=compress&cs=tinysrgb&h=350", "full_url": "https://images.pexels.com/photos/10895246/pexels-photo-10895246.jpeg?auto=compress&cs=tinysrgb&dpr=2&h=650&w=940", "extension": "jpg", "source_page_url": "https://www.pexels.com/photo/a-man-yawning-10895246/", "author_name": "Sammie Sander", "author_url": "https://www.pexels.com/@sammie-sander-165512421", "license_name": "Pexels License", "license_url": "https://www.pexels.com/license/", "fallback_full_urls": []}, {"provider_id": "pexels", "thumbnail_url": "https://images.pexels.com/photos/6541065/pexels-photo-6541065.jpeg?auto=compress&cs=tinysrgb&h=350", "full_url": "https://images.pexels.com/photos/6541065/pexels-photo-6541065.jpeg?auto=compress&cs=tinysrgb&dpr=2&h=650&w=940", "extension": "jpg", "source_page_url": "https://www.pexels.com/photo/grayscale-photo-of-woman-sleeping-6541065/", "author_name": "Polina ⠀", "author_url": "https://www.pexels.com/@polina-kovaleva", "license_name": "Pexels License", "license_url": "https://www.pexels.com/license/", "fallback_full_urls": []}, {"provider_id": "pexels", "thumbnail_url": "https://images.pexels.com/photos/7445305/pexels-photo-7445305.jpeg?auto=compress&cs=tinysrgb&h=350", "full_url": "https://images.pexels.com/photos/7445305/pexels-photo-7445305.jpeg?auto=compress&cs=tinysrgb&dpr=2&h=650&w=940", "extension": "jpg", "source_page_url": "https://www.pexels.com/photo/white-pillow-on-top-of-a-man-7445305/", "author_name": "KATRIN  BOLOVTSOVA", "author_url": "https://www.pexels.com/@ekaterina-bolovtsova", "license_name": "Pexels License", "license_url": "https://www.pexels.com/license/", "fallback_full_urls": []}, {"provider_id": "pexels", "thumbnail_url": "https://images.pexels.com/photos/6753373/pexels-photo-6753373.jpeg?auto=compress&cs=tinysrgb&h=350", "full_url": "https://images.pexels.com/photos/6753373/pexels-photo-6753373.jpeg?auto=compress&cs=tinysrgb&dpr=2&h=650&w=940", "extension": "jpg", "source_page_url": "https://www.pexels.com/photo/a-tired-woman-covered-with-blanket-while-lying-on-the-bed-6753373/", "author_name": "cottonbro studio", "author_url": "https://www.pexels.com/@cottonbro", "license_name": "Pexels License", "license_url": "https://www.pexels.com/license/", "fallback_full_urls": []}, {"provider_id": "pexels", "thumbnail_url": "https://images.pexels.com/photos/7445277/pexels-photo-7445277.jpeg?auto=compress&cs=tinysrgb&h=350", "full_url": "https://images.pexels.com/photos/7445277/pexels-photo-7445277.jpeg?auto=compress&cs=tinysrgb&dpr=2&h=650&w=940", "extension": "jpg", "source_page_url": "https://www.pexels.com/photo/a-man-in-white-shirt-sleeping-on-the-bed-7445277/", "author_name": "KATRIN  BOLOVTSOVA", "author_url": "https://www.pexels.com/@ekaterina-bolovtsova", "license_name": "Pexels License", "license_url": "https://www.pexels.com/license/", "fallback_full_urls": []}, {"provider_id": "pexels", "thumbnail_url": "https://images.pexels.com/photos/6963189/pexels-photo-6963189.jpeg?auto=compress&cs=tinysrgb&h=350", "full_url": "https://images.pexels.com/photos/6963189/pexels-photo-6963189.jpeg?auto=compress&cs=tinysrgb&dpr=2&h=650&w=940", "extension": "jpg", "source_page_url": "https://www.pexels.com/photo/woman-reaching-cellphone-in-bed-6963189/", "author_name": "cottonbro studio", "author_url": "https://www.pexels.com/@cottonbro", "license_name": "Pexels License", "license_url": "https://www.pexels.com/license/", "fallback_full_urls": []}, {"provider_id": "pexels", "thumbnail_url": "https://images.pexels.com/photos/7605198/pexels-photo-7605198.jpeg?auto=compress&cs=tinysrgb&h=350", "full_url": "https://images.pexels.com/photos/7605198/pexels-photo-7605198.jpeg?auto=compress&cs=tinysrgb&dpr=2&h=650&w=940", "extension": "jpg", "source_page_url": "https://www.pexels.com/photo/a-woman-lying-on-bed-7605198/", "author_name": "MART  PRODUCTION", "author_url": "https://www.pexels.com/@mart-production", "license_name": "Pexels License", "license_url": "https://www.pexels.com/license/", "fallback_full_urls": []}, {"provider_id": "pexels", "thumbnail_url": "https://images.pexels.com/photos/3808004/pexels-photo-3808004.jpeg?auto=compress&cs=tinysrgb&h=350", "full_url": "https://images.pexels.com/photos/3808004/pexels-photo-3808004.jpeg?auto=compress&cs=tinysrgb&dpr=2&h=650&w=940", "extension": "jpg", "source_page_url": "https://www.pexels.com/photo/woman-lying-on-bed-covering-her-face-with-her-hands-3808004/", "author_name": "Andrea Piacquadio", "author_url": "https://www.pexels.com/@olly", "license_name": "Pexels License", "license_url": "https://www.pexels.com/license/", "fallback_full_urls": []}, {"provider_id": "pexels", "thumbnail_url": "https://images.pexels.com/photos/4058791/pexels-photo-4058791.jpeg?auto=compress&cs=tinysrgb&h=350", "full_url": "https://images.pexels.com/photos/4058791/pexels-photo-4058791.jpeg?auto=compress&cs=tinysrgb&dpr=2&h=650&w=940", "extension": "jpg", "source_page_url": "https://www.pexels.com/photo/woman-night-blue-girl-4058791/", "author_name": "cottonbro studio", "author_url": "https://www.pexels.com/@cottonbro", "license_name": "Pexels License", "license_url": "https://www.pexels.com/license/", "fallback_full_urls": []}, {"provider_id": "pexels", "thumbnail_url": "https://images.pexels.com/photos/6753355/pexels-photo-6753355.jpeg?auto=compress&cs=tinysrgb&h=350", "full_url": "https://images.pexels.com/photos/6753355/pexels-photo-6753355.jpeg?auto=compress&cs=tinysrgb&dpr=2&h=650&w=940", "extension": "jpg", "source_page_url": "https://www.pexels.com/photo/a-person-lying-on-the-bed-with-eyes-closed-6753355/", "author_name": "cottonbro studio", "author_url": "https://www.pexels.com/@cottonbro", "license_name": "Pexels License", "license_url": "https://www.pexels.com/license/", "fallback_full_urls": []}, {"provider_id": "pexels", "thumbnail_url": "https://images.pexels.com/photos/8591468/pexels-photo-8591468.jpeg?auto=compress&cs=tinysrgb&h=350", "full_url": "https://images.pexels.com/photos/8591468/pexels-photo-8591468.jpeg?auto=compress&cs=tinysrgb&dpr=2&h=650&w=940", "extension": "jpg", "source_page_url": "https://www.pexels.com/photo/man-using-a-tablet-while-laying-on-the-bed-8591468/", "author_name": "cottonbro studio", "author_url": "https://www.pexels.com/@cottonbro", "license_name": "Pexels License", "license_url": "https://www.pexels.com/license/", "fallback_full_urls": []}, {"provider_id": "pexels", "thumbnail_url": "https://images.pexels.com/photos/7445213/pexels-photo-7445213.jpeg?auto=compress&cs=tinysrgb&h=350", "full_url": "https://images.pexels.com/photos/7445213/pexels-photo-7445213.jpeg?auto=compress&cs=tinysrgb&dpr=2&h=650&w=940", "extension": "jpg", "source_page_url": "https://www.pexels.com/photo/woman-lying-down-on-bed-7445213/", "author_name": "KATRIN  BOLOVTSOVA", "author_url": "https://www.pexels.com/@ekaterina-bolovtsova", "license_name": "Pexels License", "license_url": "https://www.pexels.com/license/", "fallback_full_urls": []}, {"provider_id": "pexels", "thumbnail_url": "https://images.pexels.com/photos/7445347/pexels-photo-7445347.jpeg?auto=compress&cs=tinysrgb&h=350", "full_url": "https://images.pexels.com/photos/7445347/pexels-photo-7445347.jpeg?auto=compress&cs=tinysrgb&dpr=2&h=650&w=940", "extension": "jpg", "source_page_url": "https://www.pexels.com/photo/photo-of-a-man-in-a-white-shirt-sleeping-on-the-bed-7445347/", "author_name": "KATRIN  BOLOVTSOVA", "author_url": "https://www.pexels.com/@ekaterina-bolovtsova", "license_name": "Pexels License", "license_url": "https://www.pexels.com/license/", "fallback_full_urls": []}, {"provider_id": "pexels", "thumbnail_url": "https://images.pexels.com/photos/7445294/pexels-photo-7445294.jpeg?auto=compress&cs=tinysrgb&h=350", "full_url": "https://images.pexels.com/photos/7445294/pexels-photo-7445294.jpeg?auto=compress&cs=tinysrgb&dpr=2&h=650&w=940", "extension": "jpg", "source_page_url": "https://www.pexels.com/photo/man-holding-white-pillow-while-sleeping-7445294/", "author_name": "KATRIN  BOLOVTSOVA", "author_url": "https://www.pexels.com/@ekaterina-bolovtsova", "license_name": "Pexels License", "license_url": "https://www.pexels.com/license/", "fallback_full_urls": []}, {"provider_id": "pexels", "thumbnail_url": "https://images.pexels.com/photos/8416384/pexels-photo-8416384.jpeg?auto=compress&cs=tinysrgb&h=350", "full_url": "https://images.pexels.com/photos/8416384/pexels-photo-8416384.jpeg?auto=compress&cs=tinysrgb&dpr=2&h=650&w=940", "extension": "jpg", "source_page_url": "https://www.pexels.com/photo/man-and-woman-lying-on-the-bed-8416384/", "author_name": "SHVETS production", "author_url": "https://www.pexels.com/@shvets-production", "license_name": "Pexels License", "license_url": "https://www.pexels.com/license/", "fallback_full_urls": []}, {"provider_id": "pexels", "thumbnail_url": "https://images.pexels.com/photos/6753832/pexels-photo-6753832.jpeg?auto=compress&cs=tinysrgb&h=350", "full_url": "https://images.pexels.com/photos/6753832/pexels-photo-6753832.jpeg?auto=compress&cs=tinysrgb&dpr=2&h=650&w=940", "extension": "jpg", "source_page_url": "https://www.pexels.com/photo/a-person-lying-on-front-on-bed-6753832/", "author_name": "cottonbro studio", "author_url": "https://www.pexels.com/@cottonbro", "license_name": "Pexels License", "license_url": "https://www.pexels.com/license/", "fallback_full_urls": []}, {"provider_id": "pexels", "thumbnail_url": "https://images.pexels.com/photos/8416388/pexels-photo-8416388.jpeg?auto=compress&cs=tinysrgb&h=350", "full_url": "https://images.pexels.com/photos/8416388/pexels-photo-8416388.jpeg?auto=compress&cs=tinysrgb&dpr=2&h=650&w=940", "extension": "jpg", "source_page_url": "https://www.pexels.com/photo/a-man-lying-on-the-bed-8416388/", "author_name": "SHVETS production", "author_url": "https://www.pexels.com/@shvets-production", "license_name": "Pexels License", "license_url": "https://www.pexels.com/license/", "fallback_full_urls": []}, {"provider_id": "pexels", "thumbnail_url": "https://images.pexels.com/photos/7622504/pexels-photo-7622504.jpeg?auto=compress&cs=tinysrgb&h=350", "full_url": "https://images.pexels.com/photos/7622504/pexels-photo-7622504.jpeg?auto=compress&cs=tinysrgb&dpr=2&h=650&w=940", "extension": "jpg", "source_page_url": "https://www.pexels.com/photo/young-woman-waking-up-with-alarm-clock-7622504/", "author_name": "Miriam Alonso", "author_url": "https://www.pexels.com/@miriam-alonso", "license_name": "Pexels License", "license_url": "https://www.pexels.com/license/", "fallback_full_urls": []}, {"provider_id": "pexels", "thumbnail_url": "https://images.pexels.com/photos/7445324/pexels-photo-7445324.jpeg?auto=compress&cs=tinysrgb&h=350", "full_url": "https://images.pexels.com/photos/7445324/pexels-photo-7445324.jpeg?auto=compress&cs=tinysrgb&dpr=2&h=650&w=940", "extension": "jpg", "source_page_url": "https://www.pexels.com/photo/man-sleeping-with-pillow-on-his-head-7445324/", "author_name": "KATRIN  BOLOVTSOVA", "author_url": "https://www.pexels.com/@ekaterina-bolovtsova", "license_name": "Pexels License", "license_url": "https://www.pexels.com/license/", "fallback_full_urls": []}, {"provider_id": "pexels", "thumbnail_url": "https://images.pexels.com/photos/7605188/pexels-photo-7605188.jpeg?auto=compress&cs=tinysrgb&h=350", "full_url": "https://images.pexels.com/photos/7605188/pexels-photo-7605188.jpeg?auto=compress&cs=tinysrgb&dpr=2&h=650&w=940", "extension": "jpg", "source_page_url": "https://www.pexels.com/photo/a-woman-lying-down-on-the-bed-7605188/", "author_name": "MART  PRODUCTION", "author_url": "https://www.pexels.com/@mart-production", "license_name": "Pexels License", "license_url": "https://www.pexels.com/license/", "fallback_full_urls": []}, {"provider_id": "pexels", "thumbnail_url": "https://images.pexels.com/photos/6963177/pexels-photo-6963177.jpeg?auto=compress&cs=tinysrgb&h=350", "full_url": "https://images.pexels.com/photos/6963177/pexels-photo-6963177.jpeg?auto=compress&cs=tinysrgb&dpr=2&h=650&w=940", "extension": "jpg", "source_page_url": "https://www.pexels.com/photo/young-woman-lying-in-bed-and-taking-a-selfie-6963177/", "author_name": "cottonbro studio", "author_url": "https://www.pexels.com/@cottonbro", "license_name": "Pexels License", "license_url": "https://www.pexels.com/license/", "fallback_full_urls": []}, {"provider_id": "pexels", "thumbnail_url": "https://images.pexels.com/photos/8460130/pexels-photo-8460130.jpeg?auto=compress&cs=tinysrgb&h=350", "full_url": "https://images.pexels.com/photos/8460130/pexels-photo-8460130.jpeg?auto=compress&cs=tinysrgb&dpr=2&h=650&w=940", "extension": "jpg", "source_page_url": "https://www.pexels.com/photo/a-woman-lying-on-wooden-desk-8460130/", "author_name": "Nikita Kleyman", "author_url": "https://www.pexels.com/@nikita-kleyman-69814606", "license_name": "Pexels License", "license_url": "https://www.pexels.com/license/", "fallback_full_urls": []}, {"provider_id": "pexels", "thumbnail_url": "https://images.pexels.com/photos/7445313/pexels-photo-7445313.jpeg?auto=compress&cs=tinysrgb&h=350", "full_url": "https://images.pexels.com/photos/7445313/pexels-photo-7445313.jpeg?auto=compress&cs=tinysrgb&dpr=2&h=650&w=940", "extension": "jpg", "source_page_url": "https://www.pexels.com/photo/photo-of-a-man-taking-off-his-sleep-mask-7445313/", "author_name": "KATRIN  BOLOVTSOVA", "author_url": "https://www.pexels.com/@ekaterina-bolovtsova", "license_name": "Pexels License", "license_url": "https://www.pexels.com/license/", "fallback_full_urls": []}, {"provider_id": "pexels", "thumbnail_url": "https://images.pexels.com/photos/7556597/pexels-photo-7556597.jpeg?auto=compress&cs=tinysrgb&h=350", "full_url": "https://images.pexels.com/photos/7556597/pexels-photo-7556597.jpeg?auto=compress&cs=tinysrgb&dpr=2&h=650&w=940", "extension": "jpg", "source_page_url": "https://www.pexels.com/photo/person-covering-his-face-with-pillow-7556597/", "author_name": "Kampus Production", "author_url": "https://www.pexels.com/@kampus", "license_name": "Pexels License", "license_url": "https://www.pexels.com/license/", "fallback_full_urls": []}, {"provider_id": "pexels", "thumbnail_url": "https://images.pexels.com/photos/4058796/pexels-photo-4058796.jpeg?auto=compress&cs=tinysrgb&h=350", "full_url": "https://images.pexels.com/photos/4058796/pexels-photo-4058796.jpeg?auto=compress&cs=tinysrgb&dpr=2&h=650&w=940", "extension": "jpg", "source_page_url": "https://www.pexels.com/photo/woman-girl-bed-bedroom-4058796/", "author_name": "cottonbro studio", "author_url": "https://www.pexels.com/@cottonbro", "license_name": "Pexels License", "license_url": "https://www.pexels.com/license/", "fallback_full_urls": []}, {"provider_id": "pexels", "thumbnail_url": "https://images.pexels.com/photos/3965222/pexels-photo-3965222.jpeg?auto=compress&cs=tinysrgb&h=350", "full_url": "https://images.pexels.com/photos/3965222/pexels-photo-3965222.jpeg?auto=compress&cs=tinysrgb&dpr=2&h=650&w=940", "extension": "jpg", "source_page_url": "https://www.pexels.com/photo/man-in-red-crew-neck-t-shirt-3965222/", "author_name": "Andrea Piacquadio", "author_url": "https://www.pexels.com/@olly", "license_name": "Pexels License", "license_url": "https://www.pexels.com/license/", "fallback_full_urls": []}, {"provider_id": "pexels", "thumbnail_url": "https://images.pexels.com/photos/19273998/pexels-photo-19273998.jpeg?auto=compress&cs=tinysrgb&h=350", "full_url": "https://images.pexels.com/photos/19273998/pexels-photo-19273998.jpeg?auto=compress&cs=tinysrgb&dpr=2&h=650&w=940", "extension": "jpg", "source_page_url": "https://www.pexels.com/photo/a-man-with-a-towel-on-his-forehead-and-mouth-open-sitting-inside-a-car-19273998/", "author_name": "Sergi Montaner", "author_url": "https://www.pexels.com/@sergi-montaner-1924032", "license_name": "Pexels License", "license_url": "https://www.pexels.com/license/", "fallback_full_urls": []}, {"provider_id": "pexels", "thumbnail_url": "https://images.pexels.com/photos/8453647/pexels-photo-8453647.jpeg?auto=compress&cs=tinysrgb&h=350", "full_url": "https://images.pexels.com/photos/8453647/pexels-photo-8453647.jpeg?auto=compress&cs=tinysrgb&dpr=2&h=650&w=940", "extension": "jpg", "source_page_url": "https://www.pexels.com/photo/woman-with-her-closed-eyes-wrapped-with-fabrics-8453647/", "author_name": "Ron Lach", "author_url": "https://www.pexels.com/@ron-lach", "license_name": "Pexels License", "license_url": "https://www.pexels.com/license/", "fallback_full_urls": []}, {"provider_id": "pexels", "thumbnail_url": "https://images.pexels.com/photos/22046204/pexels-photo-22046204.jpeg?auto=compress&cs=tinysrgb&h=350", "full_url": "https://images.pexels.com/photos/22046204/pexels-photo-22046204.jpeg?auto=compress&cs=tinysrgb&dpr=2&h=650&w=940", "extension": "jpg", "source_page_url": "https://www.pexels.com/photo/portrait-of-man-sleeping-on-laptop-and-table-22046204/", "author_name": "Vitaly Gariev", "author_url": "https://www.pexels.com/@silverkblack", "license_name": "Pexels License", "license_url": "https://www.pexels.com/license/", "fallback_full_urls": []}, {"provider_id": "pexels", "thumbnail_url": "https://images.pexels.com/photos/6541062/pexels-photo-6541062.jpeg?auto=compress&cs=tinysrgb&h=350", "full_url": "https://images.pexels.com/photos/6541062/pexels-photo-6541062.jpeg?auto=compress&cs=tinysrgb&dpr=2&h=650&w=940", "extension": "jpg", "source_page_url": "https://www.pexels.com/photo/close-up-photo-of-an-asleep-woman-6541062/", "author_name": "Polina ⠀", "author_url": "https://www.pexels.com/@polina-kovaleva", "license_name": "Pexels License", "license_url": "https://www.pexels.com/license/", "fallback_full_urls": []}, {"provider_id": "pexels", "thumbnail_url": "https://images.pexels.com/photos/6660784/pexels-photo-6660784.jpeg?auto=compress&cs=tinysrgb&h=350", "full_url": "https://images.pexels.com/photos/6660784/pexels-photo-6660784.jpeg?auto=compress&cs=tinysrgb&dpr=2&h=650&w=940", "extension": "jpg", "source_page_url": "https://www.pexels.com/photo/a-woman-wearing-jacket-and-eyeglasses-holding-a-book-while-lying-down-6660784/", "author_name": "www.kaboompics.com", "author_url": "https://www.pexels.com/@karola-g", "license_name": "Pexels License", "license_url": "https://www.pexels.com/license/", "fallback_full_urls": []}, {"provider_id": "pexels", "thumbnail_url": "https://images.pexels.com/photos/6951511/pexels-photo-6951511.jpeg?auto=compress&cs=tinysrgb&h=350", "full_url": "https://images.pexels.com/photos/6951511/pexels-photo-6951511.jpeg?auto=compress&cs=tinysrgb&dpr=2&h=650&w=940", "extension": "jpg", "source_page_url": "https://www.pexels.com/photo/photograph-of-a-person-with-her-hand-on-her-head-6951511/", "author_name": "cottonbro studio", "author_url": "https://www.pexels.com/@cottonbro", "license_name": "Pexels License", "license_url": "https://www.pexels.com/license/", "fallback_full_urls": []}, {"provider_id": "pexels", "thumbnail_url": "https://images.pexels.com/photos/6568105/pexels-photo-6568105.jpeg?auto=compress&cs=tinysrgb&h=350", "full_url": "https://images.pexels.com/photos/6568105/pexels-photo-6568105.jpeg?auto=compress&cs=tinysrgb&dpr=2&h=650&w=940", "extension": "jpg", "source_page_url": "https://www.pexels.com/photo/woman-wrapped-in-a-quilt-6568105/", "author_name": "cottonbro studio", "author_url": "https://www.pexels.com/@cottonbro", "license_name": "Pexels License", "license_url": "https://www.pexels.com/license/", "fallback_full_urls": []}, {"provider_id": "pexels", "thumbnail_url": "https://images.pexels.com/photos/36730543/pexels-photo-36730543.jpeg?auto=compress&cs=tinysrgb&h=350", "full_url": "https://images.pexels.com/photos/36730543/pexels-photo-36730543.jpeg?auto=compress&cs=tinysrgb&dpr=2&h=650&w=940", "extension": "jpg", "source_page_url": "https://www.pexels.com/photo/woman-feeling-anxious-in-bed-during-the-day-36730543/", "author_name": "Vitaly Gariev", "author_url": "https://www.pexels.com/@silverkblack", "license_name": "Pexels License", "license_url": "https://www.pexels.com/license/", "fallback_full_urls": []}, {"provider_id": "pexels", "thumbnail_url": "https://images.pexels.com/photos/7034748/pexels-photo-7034748.jpeg?auto=compress&cs=tinysrgb&h=350", "full_url": "https://images.pexels.com/photos/7034748/pexels-photo-7034748.jpeg?auto=compress&cs=tinysrgb&dpr=2&h=650&w=940", "extension": "jpg", "source_page_url": "https://www.pexels.com/photo/woman-sleeping-on-books-in-room-7034748/", "author_name": "George Milton", "author_url": "https://www.pexels.com/@george-milton", "license_name": "Pexels License", "license_url": "https://www.pexels.com/license/", "fallback_full_urls": []}, {"provider_id": "pexels", "thumbnail_url": "https://images.pexels.com/photos/6753366/pexels-photo-6753366.jpeg?auto=compress&cs=tinysrgb&h=350", "full_url": "https://images.pexels.com/photos/6753366/pexels-photo-6753366.jpeg?auto=compress&cs=tinysrgb&dpr=2&h=650&w=940", "extension": "jpg", "source_page_url": "https://www.pexels.com/photo/a-woman-in-pajama-lying-on-the-bed-with-blanket-6753366/", "author_name": "cottonbro studio", "author_url": "https://www.pexels.com/@cottonbro", "license_name": "Pexels License", "license_url": "https://www.pexels.com/license/", "fallback_full_urls": []}, {"provider_id": "pexels", "thumbnail_url": "https://images.pexels.com/photos/6029108/pexels-photo-6029108.jpeg?auto=compress&cs=tinysrgb&h=350", "full_url": "https://images.pexels.com/photos/6029108/pexels-photo-6029108.jpeg?auto=compress&cs=tinysrgb&dpr=2&h=650&w=940", "extension": "jpg", "source_page_url": "https://www.pexels.com/photo/woman-holding-her-laptop-6029108/", "author_name": "www.kaboompics.com", "author_url": "https://www.pexels.com/@karola-g", "license_name": "Pexels License", "license_url": "https://www.pexels.com/license/", "fallback_full_urls": []}, {"provider_id": "pexels", "thumbnail_url": "https://images.pexels.com/photos/6541063/pexels-photo-6541063.jpeg?auto=compress&cs=tinysrgb&h=350", "full_url": "https://images.pexels.com/photos/6541063/pexels-photo-6541063.jpeg?auto=compress&cs=tinysrgb&dpr=2&h=650&w=940", "extension": "jpg", "source_page_url": "https://www.pexels.com/photo/photo-of-a-woman-sleeping-6541063/", "author_name": "Polina ⠀", "author_url": "https://www.pexels.com/@polina-kovaleva", "license_name": "Pexels License", "license_url": "https://www.pexels.com/license/", "fallback_full_urls": []}, {"provider_id": "pexels", "thumbnail_url": "https://images.pexels.com/photos/6753836/pexels-photo-6753836.jpeg?auto=compress&cs=tinysrgb&h=350", "full_url": "https://images.pexels.com/photos/6753836/pexels-photo-6753836.jpeg?auto=compress&cs=tinysrgb&dpr=2&h=650&w=940", "extension": "jpg", "source_page_url": "https://www.pexels.com/photo/a-woman-lying-on-bed-holding-the-pillow-under-her-head-6753836/", "author_name": "cottonbro studio", "author_url": "https://www.pexels.com/@cottonbro", "license_name": "Pexels License", "license_url": "https://www.pexels.com/license/", "fallback_full_urls": []}, {"provider_id": "pexels", "thumbnail_url": "https://images.pexels.com/photos/36771016/pexels-photo-36771016.jpeg?auto=compress&cs=tinysrgb&h=350", "full_url": "https://images.pexels.com/photos/36771016/pexels-photo-36771016.jpeg?auto=compress&cs=tinysrgb&dpr=2&h=650&w=940", "extension": "jpg", "source_page_url": "https://www.pexels.com/photo/black-and-white-portrait-of-a-relaxed-person-indoors-36771016/", "author_name": "Nikita Pishchugin", "author_url": "https://www.pexels.com/@nikitapishchugin", "license_name": "Pexels License", "license_url": "https://www.pexels.com/license/", "fallback_full_urls": []}, {"provider_id": "pexels", "thumbnail_url": "https://images.pexels.com/photos/8472560/pexels-photo-8472560.jpeg?auto=compress&cs=tinysrgb&h=350", "full_url": "https://images.pexels.com/photos/8472560/pexels-photo-8472560.jpeg?auto=compress&cs=tinysrgb&dpr=2&h=650&w=940", "extension": "jpg", "source_page_url": "https://www.pexels.com/photo/an-overworked-man-holding-a-cup-8472560/", "author_name": "Cup of  Couple", "author_url": "https://www.pexels.com/@cup-of-couple", "license_name": "Pexels License", "license_url": "https://www.pexels.com/license/", "fallback_full_urls": []}, {"provider_id": "pexels", "thumbnail_url": "https://images.pexels.com/photos/7034611/pexels-photo-7034611.jpeg?auto=compress&cs=tinysrgb&h=350", "full_url": "https://images.pexels.com/photos/7034611/pexels-photo-7034611.jpeg?auto=compress&cs=tinysrgb&dpr=2&h=650&w=940", "extension": "jpg", "source_page_url": "https://www.pexels.com/photo/exhausted-young-woman-yawning-while-reading-textbook-in-armchair-7034611/", "author_name": "George Milton", "author_url": "https://www.pexels.com/@george-milton", "license_name": "Pexels License", "license_url": "https://www.pexels.com/license/", "fallback_full_urls": []}, {"provider_id": "pexels", "thumbnail_url": "https://images.pexels.com/photos/7445274/pexels-photo-7445274.jpeg?auto=compress&cs=tinysrgb&h=350", "full_url": "https://images.pexels.com/photos/7445274/pexels-photo-7445274.jpeg?auto=compress&cs=tinysrgb&dpr=2&h=650&w=940", "extension": "jpg", "source_page_url": "https://www.pexels.com/photo/a-man-lying-on-the-bed-7445274/", "author_name": "KATRIN  BOLOVTSOVA", "author_url": "https://www.pexels.com/@ekaterina-bolovtsova", "license_name": "Pexels License", "license_url": "https://www.pexels.com/license/", "fallback_full_urls": []}, {"provider_id": "pexels", "thumbnail_url": "https://images.pexels.com/photos/6598224/pexels-photo-6598224.jpeg?auto=compress&cs=tinysrgb&h=350", "full_url": "https://images.pexels.com/photos/6598224/pexels-photo-6598224.jpeg?auto=compress&cs=tinysrgb&dpr=2&h=650&w=940", "extension": "jpg", "source_page_url": "https://www.pexels.com/photo/a-person-covering-her-face-with-the-pillows-6598224/", "author_name": "Hanna Pad", "author_url": "https://www.pexels.com/@anna-nekrashevich", "license_name": "Pexels License", "license_url": "https://www.pexels.com/license/", "fallback_full_urls": []}, {"provider_id": "pexels", "thumbnail_url": "https://images.pexels.com/photos/6968341/pexels-photo-6968341.jpeg?auto=compress&cs=tinysrgb&h=350", "full_url": "https://images.pexels.com/photos/6968341/pexels-photo-6968341.jpeg?auto=compress&cs=tinysrgb&dpr=2&h=650&w=940", "extension": "jpg", "source_page_url": "https://www.pexels.com/photo/woman-lying-on-bed-covered-with-white-blanket-6968341/", "author_name": "Mikhail Nilov", "author_url": "https://www.pexels.com/@mikhail-nilov", "license_name": "Pexels License", "license_url": "https://www.pexels.com/license/", "fallback_full_urls": []}, {"provider_id": "pexels", "thumbnail_url": "https://images.pexels.com/photos/12585556/pexels-photo-12585556.jpeg?auto=compress&cs=tinysrgb&h=350", "full_url": "https://images.pexels.com/photos/12585556/pexels-photo-12585556.jpeg?auto=compress&cs=tinysrgb&dpr=2&h=650&w=940", "extension": "jpg", "source_page_url": "https://www.pexels.com/photo/man-sleeping-on-red-sofa-chair-12585556/", "author_name": "BOOM 💥 Photography", "author_url": "https://www.pexels.com/@boom", "license_name": "Pexels License", "license_url": "https://www.pexels.com/license/", "fallback_full_urls": []}, {"provider_id": "pexels", "thumbnail_url": "https://images.pexels.com/photos/6753369/pexels-photo-6753369.jpeg?auto=compress&cs=tinysrgb&h=350", "full_url": "https://images.pexels.com/photos/6753369/pexels-photo-6753369.jpeg?auto=compress&cs=tinysrgb&dpr=2&h=650&w=940", "extension": "jpg", "source_page_url": "https://www.pexels.com/photo/a-woman-lying-on-the-bed-with-blanket-wide-awake-6753369/", "author_name": "cottonbro studio", "author_url": "https://www.pexels.com/@cottonbro", "license_name": "Pexels License", "license_url": "https://www.pexels.com/license/", "fallback_full_urls": []}, {"provider_id": "pexels", "thumbnail_url": "https://images.pexels.com/photos/4589785/pexels-photo-4589785.jpeg?auto=compress&cs=tinysrgb&h=350", "full_url": "https://images.pexels.com/photos/4589785/pexels-photo-4589785.jpeg?auto=compress&cs=tinysrgb&dpr=2&h=650&w=940", "extension": "jpg", "source_page_url": "https://www.pexels.com/photo/woman-in-gray-sweater-lying-on-bed-with-books-and-a-laptop-4589785/", "author_name": "ArtHouse Studio", "author_url": "https://www.pexels.com/@arthousestudio", "license_name": "Pexels License", "license_url": "https://www.pexels.com/license/", "fallback_full_urls": []}, {"provider_id": "pexels", "thumbnail_url": "https://images.pexels.com/photos/8416406/pexels-photo-8416406.jpeg?auto=compress&cs=tinysrgb&h=350", "full_url": "https://images.pexels.com/photos/8416406/pexels-photo-8416406.jpeg?auto=compress&cs=tinysrgb&dpr=2&h=650&w=940", "extension": "jpg", "source_page_url": "https://www.pexels.com/photo/alarm-clocks-around-man-8416406/", "author_name": "SHVETS production", "author_url": "https://www.pexels.com/@shvets-production", "license_name": "Pexels License", "license_url": "https://www.pexels.com/license/", "fallback_full_urls": []}, {"provider_id": "pexels", "thumbnail_url": "https://images.pexels.com/photos/8560760/pexels-photo-8560760.jpeg?auto=compress&cs=tinysrgb&h=350", "full_url": "https://images.pexels.com/photos/8560760/pexels-photo-8560760.jpeg?auto=compress&cs=tinysrgb&dpr=2&h=650&w=940", "extension": "jpg", "source_page_url": "https://www.pexels.com/photo/portrait-of-a-young-man-lying-in-bed-8560760/", "author_name": "Timur Weber", "author_url": "https://www.pexels.com/@timur-weber", "license_name": "Pexels License", "license_url": "https://www.pexels.com/license/", "fallback_full_urls": []}, {"provider_id": "pexels", "thumbnail_url": "https://images.pexels.com/photos/10608003/pexels-photo-10608003.jpeg?auto=compress&cs=tinysrgb&h=350", "full_url": "https://images.pexels.com/photos/10608003/pexels-photo-10608003.jpeg?auto=compress&cs=tinysrgb&dpr=2&h=650&w=940", "extension": "jpg", "source_page_url": "https://www.pexels.com/photo/girl-rubbing-her-eyes-early-in-the-morning-10608003/", "author_name": "Ron Lach", "author_url": "https://www.pexels.com/@ron-lach", "license_name": "Pexels License", "license_url": "https://www.pexels.com/license/", "fallback_full_urls": []}, {"provider_id": "pexels", "thumbnail_url": "https://images.pexels.com/photos/8036691/pexels-photo-8036691.jpeg?auto=compress&cs=tinysrgb&h=350", "full_url": "https://images.pexels.com/photos/8036691/pexels-photo-8036691.jpeg?auto=compress&cs=tinysrgb&dpr=2&h=650&w=940", "extension": "jpg", "source_page_url": "https://www.pexels.com/photo/woman-using-a-cellphone-during-bedtime-8036691/", "author_name": "SHVETS production", "author_url": "https://www.pexels.com/@shvets-production", "license_name": "Pexels License", "license_url": "https://www.pexels.com/license/", "fallback_full_urls": []}, {"provider_id": "pexels", "thumbnail_url": "https://images.pexels.com/photos/9159052/pexels-photo-9159052.jpeg?auto=compress&cs=tinysrgb&h=350", "full_url": "https://images.pexels.com/photos/9159052/pexels-photo-9159052.jpeg?auto=compress&cs=tinysrgb&dpr=2&h=650&w=940", "extension": "jpg", "source_page_url": "https://www.pexels.com/photo/young-woman-sleeping-on-computer-keyboard-with-a-book-on-her-head-9159052/", "author_name": "Mikhail Nilov", "author_url": "https://www.pexels.com/@mikhail-nilov", "license_name": "Pexels License", "license_url": "https://www.pexels.com/license/", "fallback_full_urls": []}, {"provider_id": "pexels", "thumbnail_url": "https://images.pexels.com/photos/7623562/pexels-photo-7623562.jpeg?auto=compress&cs=tinysrgb&h=350", "full_url": "https://images.pexels.com/photos/7623562/pexels-photo-7623562.jpeg?auto=compress&cs=tinysrgb&dpr=2&h=650&w=940", "extension": "jpg", "source_page_url": "https://www.pexels.com/photo/a-woman-using-a-smartphone-7623562/", "author_name": "Miriam Alonso", "author_url": "https://www.pexels.com/@miriam-alonso", "license_name": "Pexels License", "license_url": "https://www.pexels.com/license/", "fallback_full_urls": []}, {"provider_id": "pexels", "thumbnail_url": "https://images.pexels.com/photos/6944004/pexels-photo-6944004.jpeg?auto=compress&cs=tinysrgb&h=350", "full_url": "https://images.pexels.com/photos/6944004/pexels-photo-6944004.jpeg?auto=compress&cs=tinysrgb&dpr=2&h=650&w=940", "extension": "jpg", "source_page_url": "https://www.pexels.com/photo/man-sitting-on-bed-in-morning-6944004/", "author_name": "cottonbro studio", "author_url": "https://www.pexels.com/@cottonbro", "license_name": "Pexels License", "license_url": "https://www.pexels.com/license/", "fallback_full_urls": []}, {"provider_id": "pexels", "thumbnail_url": "https://images.pexels.com/photos/8346006/pexels-photo-8346006.jpeg?auto=compress&cs=tinysrgb&h=350", "full_url": "https://images.pexels.com/photos/8346006/pexels-photo-8346006.jpeg?auto=compress&cs=tinysrgb&dpr=2&h=650&w=940", "extension": "jpg", "source_page_url": "https://www.pexels.com/photo/an-alarm-clock-on-bedside-near-a-sleeping-woman-8346006/", "author_name": "Anastasiya Vragova", "author_url": "https://www.pexels.com/@anastasiya-vragova-22991246", "license_name": "Pexels License", "license_url": "https://www.pexels.com/license/", "fallback_full_urls": []}, {"provider_id": "pexels", "thumbnail_url": "https://images.pexels.com/photos/4058788/pexels-photo-4058788.jpeg?auto=compress&cs=tinysrgb&h=350", "full_url": "https://images.pexels.com/photos/4058788/pexels-photo-4058788.jpeg?auto=compress&cs=tinysrgb&dpr=2&h=650&w=940", "extension": "jpg", "source_page_url": "https://www.pexels.com/photo/woman-girl-bed-bedroom-4058788/", "author_name": "cottonbro studio", "author_url": "https://www.pexels.com/@cottonbro", "license_name": "Pexels License", "license_url": "https://www.pexels.com/license/", "fallback_full_urls": []}, {"provider_id": "pexels", "thumbnail_url": "https://images.pexels.com/photos/4584482/pexels-photo-4584482.jpeg?auto=compress&cs=tinysrgb&h=350", "full_url": "https://images.pexels.com/photos/4584482/pexels-photo-4584482.jpeg?auto=compress&cs=tinysrgb&dpr=2&h=650&w=940", "extension": "jpg", "source_page_url": "https://www.pexels.com/photo/man-in-crew-neck-t-shirt-covering-his-mouth-4584482/", "author_name": "Ketut Subiyanto", "author_url": "https://www.pexels.com/@ketut-subiyanto", "license_name": "Pexels License", "license_url": "https://www.pexels.com/license/", "fallback_full_urls": []}]}