{"version": 1, "provider_id": "openverse", "query": "be quiet", "ts": 1779456955, "results": [{"provider_id": "openverse", "thumbnail_url": "https://api.openverse.org/v1/images/cb86a015-8064-4fca-9352-87d959f5aee6/thumb/", "full_url": "https://live.staticflickr.com/7479/16099036658_7e0594941f_b.jpg", "extension": "jpg", "source_page_url": "https://www.flickr.com/photos/55747750@N02/16099036658", "author_name": "PATRICE OUELLET", "author_url": "https://www.flickr.com/photos/55747750@N02", "license_name": "CC BY-NC-ND 2.0", "license_url": "https://creativecommons.org/licenses/by-nc-nd/2.0/", "fallback_full_urls": []}, {"provider_id": "openverse", "thumbnail_url": "https://api.openverse.org/v1/images/66dbb48f-46fa-400b-b51e-0447744f9f46/thumb/", "full_url": "https://live.staticflickr.com/324/20069820481_d35b44bb72_b.jpg", "extension": "jpg", "source_page_url": "https://www.flickr.com/photos/91835791@N02/20069820481", "author_name": "ocdeluxe", "author_url": "https://www.flickr.com/photos/91835791@N02", "license_name": "CC BY-ND 2.0", "license_url": "https://creativecommons.org/licenses/by-nd/2.0/", "fallback_full_urls": []}, {"provider_id": "openverse", "thumbnail_url": "https://api.openverse.org/v1/images/746540b8-58b4-4f4b-a44d-d841f12130c6/thumb/", "full_url": "https://live.staticflickr.com/3833/10943415714_3396f875a4_b.jpg", "extension": "jpg", "source_page_url": "https://www.flickr.com/photos/61815799@N00/10943415714", "author_name": "'J' Jose Maria Perez Nuñez", "author_url": "https://www.flickr.com/photos/61815799@N00", "license_name": "CC BY-NC 2.0", "license_url": "https://creativecommons.org/licenses/by-nc/2.0/", "fallback_full_urls": []}, {"provider_id": "openverse", "thumbnail_url": "https://api.openverse.org/v1/images/88bc98f6-a276-4cd6-8570-3e98ec2316ee/thumb/", "full_url": "https://live.staticflickr.com/3929/15344120638_5b9df721f7_b.jpg", "extension": "jpg", "source_page_url": "https://www.flickr.com/photos/62586117@N05/15344120638", "author_name": "Neil. Moralee", "author_url": "https://www.flickr.com/photos/62586117@N05", "license_name": "CC BY-NC-ND 2.0", "license_url": "https://creativecommons.org/licenses/by-nc-nd/2.0/", "fallback_full_urls": []}, {"provider_id": "openverse", "thumbnail_url": "https://api.openverse.org/v1/images/793343f7-2bc9-49ab-876f-01563613aeba/thumb/", "full_url": "https://live.staticflickr.com/7248/7622302138_ba8b2d826d_b.jpg", "extension": "jpg", "source_page_url": "https://www.flickr.com/photos/58621196@N05/7622302138", "author_name": "brdonovan", "author_url": "https://www.flickr.com/photos/58621196@N05", "license_name": "CC BY-SA 2.0", "license_url": "https://creativecommons.org/licenses/by-sa/2.0/", "fallback_full_urls": []}, {"provider_id": "openverse", "thumbnail_url": "https://api.openverse.org/v1/images/a5ee69d9-379c-4f65-b42a-2552e29061fd/thumb/", "full_url": "https://live.staticflickr.com/3226/2527053468_8a4ec7644a_b.jpg", "extension": "jpg", "source_page_url": "https://www.flickr.com/photos/95572727@N00/2527053468", "author_name": "Trey Ratcliff", "author_url": "https://www.flickr.com/photos/95572727@N00", "license_name": "CC BY-NC-SA 2.0", "license_url": "https://creativecommons.org/licenses/by-nc-sa/2.0/", "fallback_full_urls": []}, {"provider_id": "openverse", "thumbnail_url": "https://api.openverse.org/v1/images/084dc381-6550-426a-91d5-472cbeaf631a/thumb/", "full_url": "https://live.staticflickr.com/8669/29288838111_4072e2d884_b.jpg", "extension": "jpg", "source_page_url": "https://www.flickr.com/photos/94075184@N00/29288838111", "author_name": "FotoGrazio", "author_url": "https://www.flickr.com/photos/94075184@N00", "license_name": "CC BY-NC-ND 2.0", "license_url": "https://creativecommons.org/licenses/by-nc-nd/2.0/", "fallback_full_urls": []}, {"provider_id": "openverse", "thumbnail_url": "https://api.openverse.org/v1/images/325627d8-63d1-43fe-8782-b6c1994ab0b9/thumb/", "full_url": "https://live.staticflickr.com/201/493873236_69c839d6bd_b.jpg", "extension": "jpg", "source_page_url": "https://www.flickr.com/photos/93154838@N00/493873236", "author_name": "Maria Rosaria Sannino/images and words", "author_url": "https://www.flickr.com/photos/93154838@N00", "license_name": "CC BY-NC-SA 2.0", "license_url": "https://creativecommons.org/licenses/by-nc-sa/2.0/", "fallback_full_urls": []}, {"provider_id": "openverse", "thumbnail_url": "https://api.openverse.org/v1/images/b16f11b8-d0d6-4846-986d-e8bbef92a9e3/thumb/", "full_url": "https://live.staticflickr.com/3753/12570832134_240c21dfbb_b.jpg", "extension": "jpg", "source_page_url": "https://www.flickr.com/photos/42875184@N08/12570832134", "author_name": "Random__Alex", "author_url": "https://www.flickr.com/photos/42875184@N08", "license_name": "CC BY-NC 2.0", "license_url": "https://creativecommons.org/licenses/by-nc/2.0/", "fallback_full_urls": []}, {"provider_id": "openverse", "thumbnail_url": "https://api.openverse.org/v1/images/d4a2d5bc-ef0e-4c14-99a9-dd00264e2500/thumb/", "full_url": "https://live.staticflickr.com/1061/540963131_08c7661f68_b.jpg", "extension": "jpg", "source_page_url": "https://www.flickr.com/photos/8563790@N08/540963131", "author_name": "anoldent", "author_url": "https://www.flickr.com/photos/8563790@N08", "license_name": "CC BY-SA 2.0", "license_url": "https://creativecommons.org/licenses/by-sa/2.0/", "fallback_full_urls": []}, {"provider_id": "openverse", "thumbnail_url": "https://api.openverse.org/v1/images/741456e5-810f-4363-bed5-712940fff2a9/thumb/", "full_url": "https://live.staticflickr.com/8717/16725119130_7b7b31377d_b.jpg", "extension": "jpg", "source_page_url": "https://www.flickr.com/photos/25338288@N05/16725119130", "author_name": "Christopher Crouzet", "author_url": "https://www.flickr.com/photos/25338288@N05", "license_name": "CC BY 2.0", "license_url": "https://creativecommons.org/licenses/by/2.0/", "fallback_full_urls": []}, {"provider_id": "openverse", "thumbnail_url": "https://api.openverse.org/v1/images/d7778f6f-94ba-47f4-b178-8cc9294c51c8/thumb/", "full_url": "https://live.staticflickr.com/8121/8979461696_0d4242129e_b.jpg", "extension": "jpg", "source_page_url": "https://www.flickr.com/photos/45909111@N00/8979461696", "author_name": "Gwydion M. Williams", "author_url": "https://www.flickr.com/photos/45909111@N00", "license_name": "CC BY 2.0", "license_url": "https://creativecommons.org/licenses/by/2.0/", "fallback_full_urls": []}, {"provider_id": "openverse", "thumbnail_url": "https://api.openverse.org/v1/images/42fcf86a-7eed-4765-ad1b-f4ce30aec7ed/thumb/", "full_url": "https://live.staticflickr.com/3772/14077138599_7e4acda745_b.jpg", "extension": "jpg", "source_page_url": "https://www.flickr.com/photos/38134034@N04/14077138599", "author_name": "blavandmaster", "author_url": "https://www.flickr.com/photos/38134034@N04", "license_name": "CC BY-NC-SA 2.0", "license_url": "https://creativecommons.org/licenses/by-nc-sa/2.0/", "fallback_full_urls": []}, {"provider_id": "openverse", "thumbnail_url": "https://api.openverse.org/v1/images/0dd97edf-d373-4e8c-be8a-6936039fb6eb/thumb/", "full_url": "https://live.staticflickr.com/65535/48776670496_47b31aa64b_b.jpg", "extension": "jpg", "source_page_url": "https://www.flickr.com/photos/38134034@N04/48776670496", "author_name": "blavandmaster", "author_url": "https://www.flickr.com/photos/38134034@N04", "license_name": "CC BY-NC-SA 2.0", "license_url": "https://creativecommons.org/licenses/by-nc-sa/2.0/", "fallback_full_urls": []}, {"provider_id": "openverse", "thumbnail_url": "https://api.openverse.org/v1/images/0384ee05-da1b-42c3-9115-e45a953d1f7b/thumb/", "full_url": "https://live.staticflickr.com/7329/12800740215_c9046b3d42_b.jpg", "extension": "jpg", "source_page_url": "https://www.flickr.com/photos/11311685@N02/12800740215", "author_name": "chris.chabot", "author_url": "https://www.flickr.com/photos/11311685@N02", "license_name": "CC BY-NC 2.0", "license_url": "https://creativecommons.org/licenses/by-nc/2.0/", "fallback_full_urls": []}, {"provider_id": "openverse", "thumbnail_url": "https://api.openverse.org/v1/images/dbbe537d-0a9b-4abc-b398-ea4c8169e259/thumb/", "full_url": "https://live.staticflickr.com/65535/50289314808_775af6946a_b.jpg", "extension": "jpg", "source_page_url": "https://www.flickr.com/photos/53359531@N04/50289314808", "author_name": "Maurizio Fecchio", "author_url": "https://www.flickr.com/photos/53359531@N04", "license_name": "CC BY-NC-ND 2.0", "license_url": "https://creativecommons.org/licenses/by-nc-nd/2.0/", "fallback_full_urls": []}, {"provider_id": "openverse", "thumbnail_url": "https://api.openverse.org/v1/images/a66d4cbd-e1d2-4bde-a13f-08971945fa59/thumb/", "full_url": "https://live.staticflickr.com/336/19155669891_6751a38c03_b.jpg", "extension": "jpg", "source_page_url": "https://www.flickr.com/photos/132106159@N08/19155669891", "author_name": "jaralt", "author_url": "https://www.flickr.com/photos/132106159@N08", "license_name": "CC BY-NC-ND 2.0", "license_url": "https://creativecommons.org/licenses/by-nc-nd/2.0/", "fallback_full_urls": []}, {"provider_id": "openverse", "thumbnail_url": "https://api.openverse.org/v1/images/56e0e7b3-ffe4-440b-9b6a-79e85d182a9d/thumb/", "full_url": "https://live.staticflickr.com/7445/12853720893_b12cebf6d2_b.jpg", "extension": "jpg", "source_page_url": "https://www.flickr.com/photos/51035555243@N01/12853720893", "author_name": "Thomas Hawk", "author_url": "https://www.flickr.com/photos/51035555243@N01", "license_name": "CC BY-NC 2.0", "license_url": "https://creativecommons.org/licenses/by-nc/2.0/", "fallback_full_urls": []}, {"provider_id": "openverse", "thumbnail_url": "https://api.openverse.org/v1/images/cfde3bf2-fddd-414b-a029-07c708eff89a/thumb/", "full_url": "https://live.staticflickr.com/7264/27386032466_78739b9e0d_b.jpg", "extension": "jpg", "source_page_url": "https://www.flickr.com/photos/38134034@N04/27386032466", "author_name": "blavandmaster", "author_url": "https://www.flickr.com/photos/38134034@N04", "license_name": "CC BY-NC-SA 2.0", "license_url": "https://creativecommons.org/licenses/by-nc-sa/2.0/", "fallback_full_urls": []}, {"provider_id": "openverse", "thumbnail_url": "https://api.openverse.org/v1/images/c3e12488-ead2-416f-bfa4-6922904e6446/thumb/", "full_url": "https://live.staticflickr.com/2476/4039407294_3bc8ca35b3_b.jpg", "extension": "jpg", "source_page_url": "https://www.flickr.com/photos/53941347@N00/4039407294", "author_name": "jonespointfilm", "author_url": "https://www.flickr.com/photos/53941347@N00", "license_name": "CC BY 2.0", "license_url": "https://creativecommons.org/licenses/by/2.0/", "fallback_full_urls": []}]}