{"version": 1, "provider_id": "pexels", "query": "remember", "ts": 1779456876, "results": [{"provider_id": "pexels", "thumbnail_url": "https://images.pexels.com/photos/6991432/pexels-photo-6991432.jpeg?auto=compress&cs=tinysrgb&h=350", "full_url": "https://images.pexels.com/photos/6991432/pexels-photo-6991432.jpeg?auto=compress&cs=tinysrgb&dpr=2&h=650&w=940", "extension": "jpg", "source_page_url": "https://www.pexels.com/photo/a-to-remember-and-idea-words-written-on-sticky-notes-6991432/", "author_name": "DS stories", "author_url": "https://www.pexels.com/@ds-stories", "license_name": "Pexels License", "license_url": "https://www.pexels.com/license/", "fallback_full_urls": []}, {"provider_id": "pexels", "thumbnail_url": "https://images.pexels.com/photos/34331372/pexels-photo-34331372.jpeg?auto=compress&cs=tinysrgb&h=350", "full_url": "https://images.pexels.com/photos/34331372/pexels-photo-34331372.jpeg?auto=compress&cs=tinysrgb&dpr=2&h=650&w=940", "extension": "jpg", "source_page_url": "https://www.pexels.com/photo/white-rose-on-memorial-wall-with-names-34331372/", "author_name": "James L", "author_url": "https://www.pexels.com/@james-l-349383308", "license_name": "Pexels License", "license_url": "https://www.pexels.com/license/", "fallback_full_urls": []}, {"provider_id": "pexels", "thumbnail_url": "https://images.pexels.com/photos/30965506/pexels-photo-30965506.jpeg?auto=compress&cs=tinysrgb&h=350", "full_url": "https://images.pexels.com/photos/30965506/pexels-photo-30965506.jpeg?auto=compress&cs=tinysrgb&dpr=2&h=650&w=940", "extension": "jpg", "source_page_url": "https://www.pexels.com/photo/wooden-tiles-spelling-memory-on-a-table-30965506/", "author_name": "Markus Winkler", "author_url": "https://www.pexels.com/@markus-winkler-1430818", "license_name": "Pexels License", "license_url": "https://www.pexels.com/license/", "fallback_full_urls": []}, {"provider_id": "pexels", "thumbnail_url": "https://images.pexels.com/photos/29348428/pexels-photo-29348428.jpeg?auto=compress&cs=tinysrgb&h=350", "full_url": "https://images.pexels.com/photos/29348428/pexels-photo-29348428.jpeg?auto=compress&cs=tinysrgb&dpr=2&h=650&w=940", "extension": "jpg", "source_page_url": "https://www.pexels.com/photo/inspirational-quote-on-lightbox-with-drawing-29348428/", "author_name": "Renee B", "author_url": "https://www.pexels.com/@renee-b-754610178", "license_name": "Pexels License", "license_url": "https://www.pexels.com/license/", "fallback_full_urls": []}, {"provider_id": "pexels", "thumbnail_url": "https://images.pexels.com/photos/6991439/pexels-photo-6991439.jpeg?auto=compress&cs=tinysrgb&h=350", "full_url": "https://images.pexels.com/photos/6991439/pexels-photo-6991439.jpeg?auto=compress&cs=tinysrgb&dpr=2&h=650&w=940", "extension": "jpg", "source_page_url": "https://www.pexels.com/photo/sticky-notes-with-messages-on-white-background-6991439/", "author_name": "DS stories", "author_url": "https://www.pexels.com/@ds-stories", "license_name": "Pexels License", "license_url": "https://www.pexels.com/license/", "fallback_full_urls": []}, {"provider_id": "pexels", "thumbnail_url": "https://images.pexels.com/photos/34355521/pexels-photo-34355521.jpeg?auto=compress&cs=tinysrgb&h=350", "full_url": "https://images.pexels.com/photos/34355521/pexels-photo-34355521.jpeg?auto=compress&cs=tinysrgb&dpr=2&h=650&w=940", "extension": "jpg", "source_page_url": "https://www.pexels.com/photo/protest-sign-honoring-kent-state-tragedy-34355521/", "author_name": "Chris F", "author_url": "https://www.pexels.com/@chris-f-38966", "license_name": "Pexels License", "license_url": "https://www.pexels.com/license/", "fallback_full_urls": []}, {"provider_id": "pexels", "thumbnail_url": "https://images.pexels.com/photos/34937171/pexels-photo-34937171.jpeg?auto=compress&cs=tinysrgb&h=350", "full_url": "https://images.pexels.com/photos/34937171/pexels-photo-34937171.jpeg?auto=compress&cs=tinysrgb&dpr=2&h=650&w=940", "extension": "jpg", "source_page_url": "https://www.pexels.com/photo/commemorative-vigil-with-emotional-crowd-34937171/", "author_name": "Noe Garde", "author_url": "https://www.pexels.com/@noe-garde-2150865147", "license_name": "Pexels License", "license_url": "https://www.pexels.com/license/", "fallback_full_urls": []}, {"provider_id": "pexels", "thumbnail_url": "https://images.pexels.com/photos/3832028/pexels-photo-3832028.jpeg?auto=compress&cs=tinysrgb&h=350", "full_url": "https://images.pexels.com/photos/3832028/pexels-photo-3832028.jpeg?auto=compress&cs=tinysrgb&dpr=2&h=650&w=940", "extension": "jpg", "source_page_url": "https://www.pexels.com/photo/person-holding-a-book-3832028/", "author_name": "cottonbro studio", "author_url": "https://www.pexels.com/@cottonbro", "license_name": "Pexels License", "license_url": "https://www.pexels.com/license/", "fallback_full_urls": []}, {"provider_id": "pexels", "thumbnail_url": "https://images.pexels.com/photos/8532551/pexels-photo-8532551.jpeg?auto=compress&cs=tinysrgb&h=350", "full_url": "https://images.pexels.com/photos/8532551/pexels-photo-8532551.jpeg?auto=compress&cs=tinysrgb&dpr=2&h=650&w=940", "extension": "jpg", "source_page_url": "https://www.pexels.com/photo/woman-with-glass-of-red-wine-and-old-photographs-8532551/", "author_name": "www.kaboompics.com", "author_url": "https://www.pexels.com/@karola-g", "license_name": "Pexels License", "license_url": "https://www.pexels.com/license/", "fallback_full_urls": []}, {"provider_id": "pexels", "thumbnail_url": "https://images.pexels.com/photos/8143999/pexels-photo-8143999.jpeg?auto=compress&cs=tinysrgb&h=350", "full_url": "https://images.pexels.com/photos/8143999/pexels-photo-8143999.jpeg?auto=compress&cs=tinysrgb&dpr=2&h=650&w=940", "extension": "jpg", "source_page_url": "https://www.pexels.com/photo/brown-wooden-letter-tiles-on-white-surface-8143999/", "author_name": "Brett Jordan", "author_url": "https://www.pexels.com/@brettjordan", "license_name": "Pexels License", "license_url": "https://www.pexels.com/license/", "fallback_full_urls": []}, {"provider_id": "pexels", "thumbnail_url": "https://images.pexels.com/photos/16865228/pexels-photo-16865228.jpeg?auto=compress&cs=tinysrgb&h=350", "full_url": "https://images.pexels.com/photos/16865228/pexels-photo-16865228.jpeg?auto=compress&cs=tinysrgb&dpr=2&h=650&w=940", "extension": "jpg", "source_page_url": "https://www.pexels.com/photo/old-photographs-in-frames-16865228/", "author_name": "dilara irem", "author_url": "https://www.pexels.com/@dilara-irem-144475329", "license_name": "Pexels License", "license_url": "https://www.pexels.com/license/", "fallback_full_urls": []}, {"provider_id": "pexels", "thumbnail_url": "https://images.pexels.com/photos/33305508/pexels-photo-33305508.jpeg?auto=compress&cs=tinysrgb&h=350", "full_url": "https://images.pexels.com/photos/33305508/pexels-photo-33305508.jpeg?auto=compress&cs=tinysrgb&dpr=2&h=650&w=940", "extension": "jpg", "source_page_url": "https://www.pexels.com/photo/exploring-memories-through-vintage-photographs-33305508/", "author_name": "Berna", "author_url": "https://www.pexels.com/@mibernaa", "license_name": "Pexels License", "license_url": "https://www.pexels.com/license/", "fallback_full_urls": []}, {"provider_id": "pexels", "thumbnail_url": "https://images.pexels.com/photos/19040559/pexels-photo-19040559.jpeg?auto=compress&cs=tinysrgb&h=350", "full_url": "https://images.pexels.com/photos/19040559/pexels-photo-19040559.jpeg?auto=compress&cs=tinysrgb&dpr=2&h=650&w=940", "extension": "jpg", "source_page_url": "https://www.pexels.com/photo/an-old-suitcase-with-black-and-white-photos-19040559/", "author_name": "Harun", "author_url": "https://www.pexels.com/@harun-15114174", "license_name": "Pexels License", "license_url": "https://www.pexels.com/license/", "fallback_full_urls": []}, {"provider_id": "pexels", "thumbnail_url": "https://images.pexels.com/photos/33461902/pexels-photo-33461902.jpeg?auto=compress&cs=tinysrgb&h=350", "full_url": "https://images.pexels.com/photos/33461902/pexels-photo-33461902.jpeg?auto=compress&cs=tinysrgb&dpr=2&h=650&w=940", "extension": "jpg", "source_page_url": "https://www.pexels.com/photo/soldier-statue-in-front-of-historic-building-33461902/", "author_name": "Hector Portillo", "author_url": "https://www.pexels.com/@hector-portillo-1114457866", "license_name": "Pexels License", "license_url": "https://www.pexels.com/license/", "fallback_full_urls": []}, {"provider_id": "pexels", "thumbnail_url": "https://images.pexels.com/photos/31141783/pexels-photo-31141783.jpeg?auto=compress&cs=tinysrgb&h=350", "full_url": "https://images.pexels.com/photos/31141783/pexels-photo-31141783.jpeg?auto=compress&cs=tinysrgb&dpr=2&h=650&w=940", "extension": "jpg", "source_page_url": "https://www.pexels.com/photo/vintage-cameras-and-polaroid-photos-in-backpack-31141783/", "author_name": "Alexey Chudin", "author_url": "https://www.pexels.com/@chudin-alexey", "license_name": "Pexels License", "license_url": "https://www.pexels.com/license/", "fallback_full_urls": []}, {"provider_id": "pexels", "thumbnail_url": "https://images.pexels.com/photos/7772542/pexels-photo-7772542.jpeg?auto=compress&cs=tinysrgb&h=350", "full_url": "https://images.pexels.com/photos/7772542/pexels-photo-7772542.jpeg?auto=compress&cs=tinysrgb&dpr=2&h=650&w=940", "extension": "jpg", "source_page_url": "https://www.pexels.com/photo/vintage-instant-camera-in-studio-7772542/", "author_name": "Caleb Oquendo", "author_url": "https://www.pexels.com/@caleboquendo", "license_name": "Pexels License", "license_url": "https://www.pexels.com/license/", "fallback_full_urls": []}, {"provider_id": "pexels", "thumbnail_url": "https://images.pexels.com/photos/28266689/pexels-photo-28266689.jpeg?auto=compress&cs=tinysrgb&h=350", "full_url": "https://images.pexels.com/photos/28266689/pexels-photo-28266689.jpeg?auto=compress&cs=tinysrgb&dpr=2&h=650&w=940", "extension": "jpg", "source_page_url": "https://www.pexels.com/photo/vintage-cell-phone-28266689/", "author_name": "Nic Wood", "author_url": "https://www.pexels.com/@nic-scrollstoppingphotos", "license_name": "Pexels License", "license_url": "https://www.pexels.com/license/", "fallback_full_urls": []}, {"provider_id": "pexels", "thumbnail_url": "https://images.pexels.com/photos/6192128/pexels-photo-6192128.jpeg?auto=compress&cs=tinysrgb&h=350", "full_url": "https://images.pexels.com/photos/6192128/pexels-photo-6192128.jpeg?auto=compress&cs=tinysrgb&dpr=2&h=650&w=940", "extension": "jpg", "source_page_url": "https://www.pexels.com/photo/notebook-with-sticker-on-black-background-6192128/", "author_name": "KATRIN  BOLOVTSOVA", "author_url": "https://www.pexels.com/@ekaterina-bolovtsova", "license_name": "Pexels License", "license_url": "https://www.pexels.com/license/", "fallback_full_urls": []}, {"provider_id": "pexels", "thumbnail_url": "https://images.pexels.com/photos/7550317/pexels-photo-7550317.jpeg?auto=compress&cs=tinysrgb&h=350", "full_url": "https://images.pexels.com/photos/7550317/pexels-photo-7550317.jpeg?auto=compress&cs=tinysrgb&dpr=2&h=650&w=940", "extension": "jpg", "source_page_url": "https://www.pexels.com/photo/man-in-blue-denim-jacket-with-sticky-notes-on-the-face-7550317/", "author_name": "MART  PRODUCTION", "author_url": "https://www.pexels.com/@mart-production", "license_name": "Pexels License", "license_url": "https://www.pexels.com/license/", "fallback_full_urls": []}, {"provider_id": "pexels", "thumbnail_url": "https://images.pexels.com/photos/208664/pexels-photo-208664.jpeg?auto=compress&cs=tinysrgb&h=350", "full_url": "https://images.pexels.com/photos/208664/pexels-photo-208664.jpeg?auto=compress&cs=tinysrgb&dpr=2&h=650&w=940", "extension": "jpg", "source_page_url": "https://www.pexels.com/photo/body-of-water-208664/", "author_name": "Pixabay", "author_url": "https://www.pexels.com/@pixabay", "license_name": "Pexels License", "license_url": "https://www.pexels.com/license/", "fallback_full_urls": []}, {"provider_id": "pexels", "thumbnail_url": "https://images.pexels.com/photos/4082638/pexels-photo-4082638.jpeg?auto=compress&cs=tinysrgb&h=350", "full_url": "https://images.pexels.com/photos/4082638/pexels-photo-4082638.jpeg?auto=compress&cs=tinysrgb&dpr=2&h=650&w=940", "extension": "jpg", "source_page_url": "https://www.pexels.com/photo/stylish-old-fashioned-clock-on-dark-background-4082638/", "author_name": "Fredrick Eankels", "author_url": "https://www.pexels.com/@fredrick", "license_name": "Pexels License", "license_url": "https://www.pexels.com/license/", "fallback_full_urls": []}, {"provider_id": "pexels", "thumbnail_url": "https://images.pexels.com/photos/8865674/pexels-photo-8865674.jpeg?auto=compress&cs=tinysrgb&h=350", "full_url": "https://images.pexels.com/photos/8865674/pexels-photo-8865674.jpeg?auto=compress&cs=tinysrgb&dpr=2&h=650&w=940", "extension": "jpg", "source_page_url": "https://www.pexels.com/photo/a-woman-sitting-on-chair-holding-a-picture-frame-8865674/", "author_name": "RDNE Stock project", "author_url": "https://www.pexels.com/@rdne", "license_name": "Pexels License", "license_url": "https://www.pexels.com/license/", "fallback_full_urls": []}, {"provider_id": "pexels", "thumbnail_url": "https://images.pexels.com/photos/4082637/pexels-photo-4082637.jpeg?auto=compress&cs=tinysrgb&h=350", "full_url": "https://images.pexels.com/photos/4082637/pexels-photo-4082637.jpeg?auto=compress&cs=tinysrgb&dpr=2&h=650&w=940", "extension": "jpg", "source_page_url": "https://www.pexels.com/photo/old-fashioned-round-watch-in-dark-room-4082637/", "author_name": "Fredrick Eankels", "author_url": "https://www.pexels.com/@fredrick", "license_name": "Pexels License", "license_url": "https://www.pexels.com/license/", "fallback_full_urls": []}, {"provider_id": "pexels", "thumbnail_url": "https://images.pexels.com/photos/18524140/pexels-photo-18524140.jpeg?auto=compress&cs=tinysrgb&h=350", "full_url": "https://images.pexels.com/photos/18524140/pexels-photo-18524140.jpeg?auto=compress&cs=tinysrgb&dpr=2&h=650&w=940", "extension": "jpg", "source_page_url": "https://www.pexels.com/photo/scrabble-tiles-with-the-word-ruckblick-written-on-them-18524140/", "author_name": "Markus Winkler", "author_url": "https://www.pexels.com/@markus-winkler-1430818", "license_name": "Pexels License", "license_url": "https://www.pexels.com/license/", "fallback_full_urls": []}, {"provider_id": "pexels", "thumbnail_url": "https://images.pexels.com/photos/33344612/pexels-photo-33344612.jpeg?auto=compress&cs=tinysrgb&h=350", "full_url": "https://images.pexels.com/photos/33344612/pexels-photo-33344612.jpeg?auto=compress&cs=tinysrgb&dpr=2&h=650&w=940", "extension": "jpg", "source_page_url": "https://www.pexels.com/photo/desk-organizer-with-sticky-notes-and-pen-33344612/", "author_name": "Petra Ryan", "author_url": "https://www.pexels.com/@petraryan", "license_name": "Pexels License", "license_url": "https://www.pexels.com/license/", "fallback_full_urls": []}, {"provider_id": "pexels", "thumbnail_url": "https://images.pexels.com/photos/35304251/pexels-photo-35304251.jpeg?auto=compress&cs=tinysrgb&h=350", "full_url": "https://images.pexels.com/photos/35304251/pexels-photo-35304251.jpeg?auto=compress&cs=tinysrgb&dpr=2&h=650&w=940", "extension": "jpg", "source_page_url": "https://www.pexels.com/photo/white-rose-on-9-11-memorial-in-nyc-35304251/", "author_name": "Victor Zhang", "author_url": "https://www.pexels.com/@victor-zhang-2147713884", "license_name": "Pexels License", "license_url": "https://www.pexels.com/license/", "fallback_full_urls": []}, {"provider_id": "pexels", "thumbnail_url": "https://images.pexels.com/photos/8174080/pexels-photo-8174080.jpeg?auto=compress&cs=tinysrgb&h=350", "full_url": "https://images.pexels.com/photos/8174080/pexels-photo-8174080.jpeg?auto=compress&cs=tinysrgb&dpr=2&h=650&w=940", "extension": "jpg", "source_page_url": "https://www.pexels.com/photo/close-up-of-a-person-holding-a-flower-8174080/", "author_name": "Vlad Ioan", "author_url": "https://www.pexels.com/@vlad-ioan-21692766", "license_name": "Pexels License", "license_url": "https://www.pexels.com/license/", "fallback_full_urls": []}, {"provider_id": "pexels", "thumbnail_url": "https://images.pexels.com/photos/13092778/pexels-photo-13092778.jpeg?auto=compress&cs=tinysrgb&h=350", "full_url": "https://images.pexels.com/photos/13092778/pexels-photo-13092778.jpeg?auto=compress&cs=tinysrgb&dpr=2&h=650&w=940", "extension": "jpg", "source_page_url": "https://www.pexels.com/photo/a-person-holding-a-piece-of-paper-with-the-word-today-13092778/", "author_name": "Image Hunter", "author_url": "https://www.pexels.com/@image-hunter-281453274", "license_name": "Pexels License", "license_url": "https://www.pexels.com/license/", "fallback_full_urls": []}, {"provider_id": "pexels", "thumbnail_url": "https://images.pexels.com/photos/18524151/pexels-photo-18524151.jpeg?auto=compress&cs=tinysrgb&h=350", "full_url": "https://images.pexels.com/photos/18524151/pexels-photo-18524151.jpeg?auto=compress&cs=tinysrgb&dpr=2&h=650&w=940", "extension": "jpg", "source_page_url": "https://www.pexels.com/photo/scrabble-tiles-with-the-word-ruckblick-written-on-them-18524151/", "author_name": "Markus Winkler", "author_url": "https://www.pexels.com/@markus-winkler-1430818", "license_name": "Pexels License", "license_url": "https://www.pexels.com/license/", "fallback_full_urls": []}, {"provider_id": "pexels", "thumbnail_url": "https://images.pexels.com/photos/13913991/pexels-photo-13913991.jpeg?auto=compress&cs=tinysrgb&h=350", "full_url": "https://images.pexels.com/photos/13913991/pexels-photo-13913991.jpeg?auto=compress&cs=tinysrgb&dpr=2&h=650&w=940", "extension": "jpg", "source_page_url": "https://www.pexels.com/photo/close-up-of-a-heart-with-a-phrase-13913991/", "author_name": "wr heustis", "author_url": "https://www.pexels.com/@wr-heustis-310270240", "license_name": "Pexels License", "license_url": "https://www.pexels.com/license/", "fallback_full_urls": []}, {"provider_id": "pexels", "thumbnail_url": "https://images.pexels.com/photos/11465614/pexels-photo-11465614.jpeg?auto=compress&cs=tinysrgb&h=350", "full_url": "https://images.pexels.com/photos/11465614/pexels-photo-11465614.jpeg?auto=compress&cs=tinysrgb&dpr=2&h=650&w=940", "extension": "jpg", "source_page_url": "https://www.pexels.com/photo/text-on-a-concrete-wall-11465614/", "author_name": "Atlantic Ambience", "author_url": "https://www.pexels.com/@freestockpro", "license_name": "Pexels License", "license_url": "https://www.pexels.com/license/", "fallback_full_urls": []}, {"provider_id": "pexels", "thumbnail_url": "https://images.pexels.com/photos/34135759/pexels-photo-34135759.jpeg?auto=compress&cs=tinysrgb&h=350", "full_url": "https://images.pexels.com/photos/34135759/pexels-photo-34135759.jpeg?auto=compress&cs=tinysrgb&dpr=2&h=650&w=940", "extension": "jpg", "source_page_url": "https://www.pexels.com/photo/statue-hands-with-poppy-flower-in-liverpool-34135759/", "author_name": "Mike Norris", "author_url": "https://www.pexels.com/@miken", "license_name": "Pexels License", "license_url": "https://www.pexels.com/license/", "fallback_full_urls": []}, {"provider_id": "pexels", "thumbnail_url": "https://images.pexels.com/photos/3832032/pexels-photo-3832032.jpeg?auto=compress&cs=tinysrgb&h=350", "full_url": "https://images.pexels.com/photos/3832032/pexels-photo-3832032.jpeg?auto=compress&cs=tinysrgb&dpr=2&h=650&w=940", "extension": "jpg", "source_page_url": "https://www.pexels.com/photo/person-holding-a-book-3832032/", "author_name": "cottonbro studio", "author_url": "https://www.pexels.com/@cottonbro", "license_name": "Pexels License", "license_url": "https://www.pexels.com/license/", "fallback_full_urls": []}, {"provider_id": "pexels", "thumbnail_url": "https://images.pexels.com/photos/5966947/pexels-photo-5966947.jpeg?auto=compress&cs=tinysrgb&h=350", "full_url": "https://images.pexels.com/photos/5966947/pexels-photo-5966947.jpeg?auto=compress&cs=tinysrgb&dpr=2&h=650&w=940", "extension": "jpg", "source_page_url": "https://www.pexels.com/photo/red-puppies-on-crosses-in-cemetery-5966947/", "author_name": "Nathan J Hilton", "author_url": "https://www.pexels.com/@nathanjhilton", "license_name": "Pexels License", "license_url": "https://www.pexels.com/license/", "fallback_full_urls": []}, {"provider_id": "pexels", "thumbnail_url": "https://images.pexels.com/photos/19743555/pexels-photo-19743555.jpeg?auto=compress&cs=tinysrgb&h=350", "full_url": "https://images.pexels.com/photos/19743555/pexels-photo-19743555.jpeg?auto=compress&cs=tinysrgb&dpr=2&h=650&w=940", "extension": "jpg", "source_page_url": "https://www.pexels.com/photo/colorful-dots-around-question-text-19743555/", "author_name": "Michaela St", "author_url": "https://www.pexels.com/@michaela-st-3448542", "license_name": "Pexels License", "license_url": "https://www.pexels.com/license/", "fallback_full_urls": []}, {"provider_id": "pexels", "thumbnail_url": "https://images.pexels.com/photos/8015673/pexels-photo-8015673.jpeg?auto=compress&cs=tinysrgb&h=350", "full_url": "https://images.pexels.com/photos/8015673/pexels-photo-8015673.jpeg?auto=compress&cs=tinysrgb&dpr=2&h=650&w=940", "extension": "jpg", "source_page_url": "https://www.pexels.com/photo/person-holding-a-pen-over-a-white-cloud-bubble-speech-8015673/", "author_name": "Cup of  Couple", "author_url": "https://www.pexels.com/@cup-of-couple", "license_name": "Pexels License", "license_url": "https://www.pexels.com/license/", "fallback_full_urls": []}, {"provider_id": "pexels", "thumbnail_url": "https://images.pexels.com/photos/7614817/pexels-photo-7614817.jpeg?auto=compress&cs=tinysrgb&h=350", "full_url": "https://images.pexels.com/photos/7614817/pexels-photo-7614817.jpeg?auto=compress&cs=tinysrgb&dpr=2&h=650&w=940", "extension": "jpg", "source_page_url": "https://www.pexels.com/photo/memorial-for-victims-of-german-occupation-in-budapest-hungary-7614817/", "author_name": "KITSUN YUEN", "author_url": "https://www.pexels.com/@kitsun-yuen-49565104", "license_name": "Pexels License", "license_url": "https://www.pexels.com/license/", "fallback_full_urls": []}, {"provider_id": "pexels", "thumbnail_url": "https://images.pexels.com/photos/34777327/pexels-photo-34777327.jpeg?auto=compress&cs=tinysrgb&h=350", "full_url": "https://images.pexels.com/photos/34777327/pexels-photo-34777327.jpeg?auto=compress&cs=tinysrgb&dpr=2&h=650&w=940", "extension": "jpg", "source_page_url": "https://www.pexels.com/photo/votive-candles-in-a-dutch-church-setting-34777327/", "author_name": "Ros NL", "author_url": "https://www.pexels.com/@rosdel", "license_name": "Pexels License", "license_url": "https://www.pexels.com/license/", "fallback_full_urls": []}, {"provider_id": "pexels", "thumbnail_url": "https://images.pexels.com/photos/34249857/pexels-photo-34249857.jpeg?auto=compress&cs=tinysrgb&h=350", "full_url": "https://images.pexels.com/photos/34249857/pexels-photo-34249857.jpeg?auto=compress&cs=tinysrgb&dpr=2&h=650&w=940", "extension": "jpg", "source_page_url": "https://www.pexels.com/photo/traditional-asian-pavilion-in-lush-garden-setting-34249857/", "author_name": "女子 正真", "author_url": "https://www.pexels.com/@1433506698", "license_name": "Pexels License", "license_url": "https://www.pexels.com/license/", "fallback_full_urls": []}, {"provider_id": "pexels", "thumbnail_url": "https://images.pexels.com/photos/29026109/pexels-photo-29026109.jpeg?auto=compress&cs=tinysrgb&h=350", "full_url": "https://images.pexels.com/photos/29026109/pexels-photo-29026109.jpeg?auto=compress&cs=tinysrgb&dpr=2&h=650&w=940", "extension": "jpg", "source_page_url": "https://www.pexels.com/photo/elderly-man-walking-in-serene-cemetery-during-fall-29026109/", "author_name": "Duygu", "author_url": "https://www.pexels.com/@duygugungor", "license_name": "Pexels License", "license_url": "https://www.pexels.com/license/", "fallback_full_urls": []}, {"provider_id": "pexels", "thumbnail_url": "https://images.pexels.com/photos/22682101/pexels-photo-22682101.jpeg?auto=compress&cs=tinysrgb&h=350", "full_url": "https://images.pexels.com/photos/22682101/pexels-photo-22682101.jpeg?auto=compress&cs=tinysrgb&dpr=2&h=650&w=940", "extension": "jpg", "source_page_url": "https://www.pexels.com/photo/person-with-carnation-in-cap-22682101/", "author_name": "Diogo Miranda", "author_url": "https://www.pexels.com/@diogo-miranda-2044514", "license_name": "Pexels License", "license_url": "https://www.pexels.com/license/", "fallback_full_urls": []}, {"provider_id": "pexels", "thumbnail_url": "https://images.pexels.com/photos/36598331/pexels-photo-36598331.jpeg?auto=compress&cs=tinysrgb&h=350", "full_url": "https://images.pexels.com/photos/36598331/pexels-photo-36598331.jpeg?auto=compress&cs=tinysrgb&dpr=2&h=650&w=940", "extension": "jpg", "source_page_url": "https://www.pexels.com/photo/open-notebook-with-pen-in-natural-light-36598331/", "author_name": "Taiye Salawu", "author_url": "https://www.pexels.com/@taiyesalawu", "license_name": "Pexels License", "license_url": "https://www.pexels.com/license/", "fallback_full_urls": []}, {"provider_id": "pexels", "thumbnail_url": "https://images.pexels.com/photos/1533205/pexels-photo-1533205.jpeg?auto=compress&cs=tinysrgb&h=350", "full_url": "https://images.pexels.com/photos/1533205/pexels-photo-1533205.jpeg?auto=compress&cs=tinysrgb&dpr=2&h=650&w=940", "extension": "jpg", "source_page_url": "https://www.pexels.com/photo/person-holding-remember-in-november-sign-1533205/", "author_name": "Rosemary Ketchum", "author_url": "https://www.pexels.com/@ketchumcommunity", "license_name": "Pexels License", "license_url": "https://www.pexels.com/license/", "fallback_full_urls": []}, {"provider_id": "pexels", "thumbnail_url": "https://images.pexels.com/photos/8865100/pexels-photo-8865100.jpeg?auto=compress&cs=tinysrgb&h=350", "full_url": "https://images.pexels.com/photos/8865100/pexels-photo-8865100.jpeg?auto=compress&cs=tinysrgb&dpr=2&h=650&w=940", "extension": "jpg", "source_page_url": "https://www.pexels.com/photo/woman-in-black-dress-offering-flowers-on-a-grave-8865100/", "author_name": "RDNE Stock project", "author_url": "https://www.pexels.com/@rdne", "license_name": "Pexels License", "license_url": "https://www.pexels.com/license/", "fallback_full_urls": []}, {"provider_id": "pexels", "thumbnail_url": "https://images.pexels.com/photos/34777725/pexels-photo-34777725.jpeg?auto=compress&cs=tinysrgb&h=350", "full_url": "https://images.pexels.com/photos/34777725/pexels-photo-34777725.jpeg?auto=compress&cs=tinysrgb&dpr=2&h=650&w=940", "extension": "jpg", "source_page_url": "https://www.pexels.com/photo/delicate-red-poppy-in-gentle-hand-34777725/", "author_name": "Mehmet", "author_url": "https://www.pexels.com/@mehmet", "license_name": "Pexels License", "license_url": "https://www.pexels.com/license/", "fallback_full_urls": []}, {"provider_id": "pexels", "thumbnail_url": "https://images.pexels.com/photos/34777726/pexels-photo-34777726.jpeg?auto=compress&cs=tinysrgb&h=350", "full_url": "https://images.pexels.com/photos/34777726/pexels-photo-34777726.jpeg?auto=compress&cs=tinysrgb&dpr=2&h=650&w=940", "extension": "jpg", "source_page_url": "https://www.pexels.com/photo/hand-reaching-towards-vibrant-red-poppy-flower-34777726/", "author_name": "Mehmet", "author_url": "https://www.pexels.com/@mehmet", "license_name": "Pexels License", "license_url": "https://www.pexels.com/license/", "fallback_full_urls": []}, {"provider_id": "pexels", "thumbnail_url": "https://images.pexels.com/photos/19953986/pexels-photo-19953986.jpeg?auto=compress&cs=tinysrgb&h=350", "full_url": "https://images.pexels.com/photos/19953986/pexels-photo-19953986.jpeg?auto=compress&cs=tinysrgb&dpr=2&h=650&w=940", "extension": "jpg", "source_page_url": "https://www.pexels.com/photo/telephone-kiosk-19953986/", "author_name": "Efrem  Efre", "author_url": "https://www.pexels.com/@efrem-efre-2786187", "license_name": "Pexels License", "license_url": "https://www.pexels.com/license/", "fallback_full_urls": []}, {"provider_id": "pexels", "thumbnail_url": "https://images.pexels.com/photos/8607506/pexels-photo-8607506.jpeg?auto=compress&cs=tinysrgb&h=350", "full_url": "https://images.pexels.com/photos/8607506/pexels-photo-8607506.jpeg?auto=compress&cs=tinysrgb&dpr=2&h=650&w=940", "extension": "jpg", "source_page_url": "https://www.pexels.com/photo/a-sculpture-of-a-soldier-holding-a-rifle-8607506/", "author_name": "Erik Mclean", "author_url": "https://www.pexels.com/@introspectivedsgn", "license_name": "Pexels License", "license_url": "https://www.pexels.com/license/", "fallback_full_urls": []}, {"provider_id": "pexels", "thumbnail_url": "https://images.pexels.com/photos/7615615/pexels-photo-7615615.jpeg?auto=compress&cs=tinysrgb&h=350", "full_url": "https://images.pexels.com/photos/7615615/pexels-photo-7615615.jpeg?auto=compress&cs=tinysrgb&dpr=2&h=650&w=940", "extension": "jpg", "source_page_url": "https://www.pexels.com/photo/happy-new-year-greeting-card-7615615/", "author_name": "Nataliya Vaitkevich", "author_url": "https://www.pexels.com/@n-voitkevich", "license_name": "Pexels License", "license_url": "https://www.pexels.com/license/", "fallback_full_urls": []}, {"provider_id": "pexels", "thumbnail_url": "https://images.pexels.com/photos/8865073/pexels-photo-8865073.jpeg?auto=compress&cs=tinysrgb&h=350", "full_url": "https://images.pexels.com/photos/8865073/pexels-photo-8865073.jpeg?auto=compress&cs=tinysrgb&dpr=2&h=650&w=940", "extension": "jpg", "source_page_url": "https://www.pexels.com/photo/red-flowers-and-candle-on-a-tomb-8865073/", "author_name": "RDNE Stock project", "author_url": "https://www.pexels.com/@rdne", "license_name": "Pexels License", "license_url": "https://www.pexels.com/license/", "fallback_full_urls": []}, {"provider_id": "pexels", "thumbnail_url": "https://images.pexels.com/photos/6486893/pexels-photo-6486893.jpeg?auto=compress&cs=tinysrgb&h=350", "full_url": "https://images.pexels.com/photos/6486893/pexels-photo-6486893.jpeg?auto=compress&cs=tinysrgb&dpr=2&h=650&w=940", "extension": "jpg", "source_page_url": "https://www.pexels.com/photo/a-back-view-of-a-woman-in-a-flower-field-6486893/", "author_name": "Eugene Lisyuk", "author_url": "https://www.pexels.com/@eugenelisyuk", "license_name": "Pexels License", "license_url": "https://www.pexels.com/license/", "fallback_full_urls": []}, {"provider_id": "pexels", "thumbnail_url": "https://images.pexels.com/photos/15380264/pexels-photo-15380264.jpeg?auto=compress&cs=tinysrgb&h=350", "full_url": "https://images.pexels.com/photos/15380264/pexels-photo-15380264.jpeg?auto=compress&cs=tinysrgb&dpr=2&h=650&w=940", "extension": "jpg", "source_page_url": "https://www.pexels.com/photo/photo-of-cubes-with-letters-forming-the-word-repeat-15380264/", "author_name": "Ann H", "author_url": "https://www.pexels.com/@ann-h-45017", "license_name": "Pexels License", "license_url": "https://www.pexels.com/license/", "fallback_full_urls": []}, {"provider_id": "pexels", "thumbnail_url": "https://images.pexels.com/photos/36598332/pexels-photo-36598332.jpeg?auto=compress&cs=tinysrgb&h=350", "full_url": "https://images.pexels.com/photos/36598332/pexels-photo-36598332.jpeg?auto=compress&cs=tinysrgb&dpr=2&h=650&w=940", "extension": "jpg", "source_page_url": "https://www.pexels.com/photo/open-notebook-with-shadows-and-pen-in-sunlight-36598332/", "author_name": "Taiye Salawu", "author_url": "https://www.pexels.com/@taiyesalawu", "license_name": "Pexels License", "license_url": "https://www.pexels.com/license/", "fallback_full_urls": []}, {"provider_id": "pexels", "thumbnail_url": "https://images.pexels.com/photos/34777692/pexels-photo-34777692.jpeg?auto=compress&cs=tinysrgb&h=350", "full_url": "https://images.pexels.com/photos/34777692/pexels-photo-34777692.jpeg?auto=compress&cs=tinysrgb&dpr=2&h=650&w=940", "extension": "jpg", "source_page_url": "https://www.pexels.com/photo/hand-reaching-towards-red-poppy-flowers-in-garden-34777692/", "author_name": "Mehmet", "author_url": "https://www.pexels.com/@mehmet", "license_name": "Pexels License", "license_url": "https://www.pexels.com/license/", "fallback_full_urls": []}, {"provider_id": "pexels", "thumbnail_url": "https://images.pexels.com/photos/10997642/pexels-photo-10997642.jpeg?auto=compress&cs=tinysrgb&h=350", "full_url": "https://images.pexels.com/photos/10997642/pexels-photo-10997642.jpeg?auto=compress&cs=tinysrgb&dpr=2&h=650&w=940", "extension": "jpg", "source_page_url": "https://www.pexels.com/photo/pen-on-graphing-paper-10997642/", "author_name": "Nathan J Hilton", "author_url": "https://www.pexels.com/@nathanjhilton", "license_name": "Pexels License", "license_url": "https://www.pexels.com/license/", "fallback_full_urls": []}, {"provider_id": "pexels", "thumbnail_url": "https://images.pexels.com/photos/8371491/pexels-photo-8371491.jpeg?auto=compress&cs=tinysrgb&h=350", "full_url": "https://images.pexels.com/photos/8371491/pexels-photo-8371491.jpeg?auto=compress&cs=tinysrgb&dpr=2&h=650&w=940", "extension": "jpg", "source_page_url": "https://www.pexels.com/photo/woman-holding-poppy-flowers-and-a-book-8371491/", "author_name": "Наталья Водопад", "author_url": "https://www.pexels.com/@69813652", "license_name": "Pexels License", "license_url": "https://www.pexels.com/license/", "fallback_full_urls": []}, {"provider_id": "pexels", "thumbnail_url": "https://images.pexels.com/photos/31983047/pexels-photo-31983047.jpeg?auto=compress&cs=tinysrgb&h=350", "full_url": "https://images.pexels.com/photos/31983047/pexels-photo-31983047.jpeg?auto=compress&cs=tinysrgb&dpr=2&h=650&w=940", "extension": "jpg", "source_page_url": "https://www.pexels.com/photo/silhouette-of-woman-enjoying-nature-at-sunset-31983047/", "author_name": "Djordje Ristic", "author_url": "https://www.pexels.com/@djordje-ristic-3727896", "license_name": "Pexels License", "license_url": "https://www.pexels.com/license/", "fallback_full_urls": []}, {"provider_id": "pexels", "thumbnail_url": "https://images.pexels.com/photos/12106195/pexels-photo-12106195.jpeg?auto=compress&cs=tinysrgb&h=350", "full_url": "https://images.pexels.com/photos/12106195/pexels-photo-12106195.jpeg?auto=compress&cs=tinysrgb&dpr=2&h=650&w=940", "extension": "jpg", "source_page_url": "https://www.pexels.com/photo/fingers-holding-sheet-with-text-12106195/", "author_name": "Антон Злобин", "author_url": "https://www.pexels.com/@dellsad", "license_name": "Pexels License", "license_url": "https://www.pexels.com/license/", "fallback_full_urls": []}, {"provider_id": "pexels", "thumbnail_url": "https://images.pexels.com/photos/8016930/pexels-photo-8016930.jpeg?auto=compress&cs=tinysrgb&h=350", "full_url": "https://images.pexels.com/photos/8016930/pexels-photo-8016930.jpeg?auto=compress&cs=tinysrgb&dpr=2&h=650&w=940", "extension": "jpg", "source_page_url": "https://www.pexels.com/photo/keep-your-head-up-8016930/", "author_name": "Anna Tarazevich", "author_url": "https://www.pexels.com/@anntarazevich", "license_name": "Pexels License", "license_url": "https://www.pexels.com/license/", "fallback_full_urls": []}, {"provider_id": "pexels", "thumbnail_url": "https://images.pexels.com/photos/12147178/pexels-photo-12147178.jpeg?auto=compress&cs=tinysrgb&h=350", "full_url": "https://images.pexels.com/photos/12147178/pexels-photo-12147178.jpeg?auto=compress&cs=tinysrgb&dpr=2&h=650&w=940", "extension": "jpg", "source_page_url": "https://www.pexels.com/photo/close-up-photo-of-blooming-poppy-flower-12147178/", "author_name": "Pavlos Nastas", "author_url": "https://www.pexels.com/@pavlos-nastas-233482117", "license_name": "Pexels License", "license_url": "https://www.pexels.com/license/", "fallback_full_urls": []}, {"provider_id": "pexels", "thumbnail_url": "https://images.pexels.com/photos/37671203/pexels-photo-37671203.jpeg?auto=compress&cs=tinysrgb&h=350", "full_url": "https://images.pexels.com/photos/37671203/pexels-photo-37671203.jpeg?auto=compress&cs=tinysrgb&dpr=2&h=650&w=940", "extension": "jpg", "source_page_url": "https://www.pexels.com/photo/rustic-brick-wall-with-seashell-adornments-37671203/", "author_name": "Christina & Peter", "author_url": "https://www.pexels.com/@christina99999", "license_name": "Pexels License", "license_url": "https://www.pexels.com/license/", "fallback_full_urls": []}, {"provider_id": "pexels", "thumbnail_url": "https://images.pexels.com/photos/29456222/pexels-photo-29456222.jpeg?auto=compress&cs=tinysrgb&h=350", "full_url": "https://images.pexels.com/photos/29456222/pexels-photo-29456222.jpeg?auto=compress&cs=tinysrgb&dpr=2&h=650&w=940", "extension": "jpg", "source_page_url": "https://www.pexels.com/photo/inspirational-quote-on-practicing-gratitude-29456222/", "author_name": "Anurag Jamwal", "author_url": "https://www.pexels.com/@aj4xo", "license_name": "Pexels License", "license_url": "https://www.pexels.com/license/", "fallback_full_urls": []}, {"provider_id": "pexels", "thumbnail_url": "https://images.pexels.com/photos/8865060/pexels-photo-8865060.jpeg?auto=compress&cs=tinysrgb&h=350", "full_url": "https://images.pexels.com/photos/8865060/pexels-photo-8865060.jpeg?auto=compress&cs=tinysrgb&dpr=2&h=650&w=940", "extension": "jpg", "source_page_url": "https://www.pexels.com/photo/woman-in-black-clothes-walking-on-grass-inside-a-cemetery-8865060/", "author_name": "RDNE Stock project", "author_url": "https://www.pexels.com/@rdne", "license_name": "Pexels License", "license_url": "https://www.pexels.com/license/", "fallback_full_urls": []}, {"provider_id": "pexels", "thumbnail_url": "https://images.pexels.com/photos/14102369/pexels-photo-14102369.jpeg?auto=compress&cs=tinysrgb&h=350", "full_url": "https://images.pexels.com/photos/14102369/pexels-photo-14102369.jpeg?auto=compress&cs=tinysrgb&dpr=2&h=650&w=940", "extension": "jpg", "source_page_url": "https://www.pexels.com/photo/shoes-on-the-danube-bank-in-budapest-14102369/", "author_name": "Laura vg", "author_url": "https://www.pexels.com/@laura-vg-345256709", "license_name": "Pexels License", "license_url": "https://www.pexels.com/license/", "fallback_full_urls": []}, {"provider_id": "pexels", "thumbnail_url": "https://images.pexels.com/photos/10258031/pexels-photo-10258031.jpeg?auto=compress&cs=tinysrgb&h=350", "full_url": "https://images.pexels.com/photos/10258031/pexels-photo-10258031.jpeg?auto=compress&cs=tinysrgb&dpr=2&h=650&w=940", "extension": "jpg", "source_page_url": "https://www.pexels.com/photo/man-walking-in-the-cemetery-10258031/", "author_name": "Brett Sayles", "author_url": "https://www.pexels.com/@brett-sayles", "license_name": "Pexels License", "license_url": "https://www.pexels.com/license/", "fallback_full_urls": []}, {"provider_id": "pexels", "thumbnail_url": "https://images.pexels.com/photos/7943481/pexels-photo-7943481.jpeg?auto=compress&cs=tinysrgb&h=350", "full_url": "https://images.pexels.com/photos/7943481/pexels-photo-7943481.jpeg?auto=compress&cs=tinysrgb&dpr=2&h=650&w=940", "extension": "jpg", "source_page_url": "https://www.pexels.com/photo/girl-in-a-green-shirt-playing-with-cards-7943481/", "author_name": "Nicola Barts", "author_url": "https://www.pexels.com/@nicola-barts", "license_name": "Pexels License", "license_url": "https://www.pexels.com/license/", "fallback_full_urls": []}, {"provider_id": "pexels", "thumbnail_url": "https://images.pexels.com/photos/27504976/pexels-photo-27504976.jpeg?auto=compress&cs=tinysrgb&h=350", "full_url": "https://images.pexels.com/photos/27504976/pexels-photo-27504976.jpeg?auto=compress&cs=tinysrgb&dpr=2&h=650&w=940", "extension": "jpg", "source_page_url": "https://www.pexels.com/photo/a-black-and-white-photo-of-a-cemetery-27504976/", "author_name": "Jude Mitchell-Hedges", "author_url": "https://www.pexels.com/@jude-mitchell-hedges-3572697", "license_name": "Pexels License", "license_url": "https://www.pexels.com/license/", "fallback_full_urls": []}, {"provider_id": "pexels", "thumbnail_url": "https://images.pexels.com/photos/35967972/pexels-photo-35967972.jpeg?auto=compress&cs=tinysrgb&h=350", "full_url": "https://images.pexels.com/photos/35967972/pexels-photo-35967972.jpeg?auto=compress&cs=tinysrgb&dpr=2&h=650&w=940", "extension": "jpg", "source_page_url": "https://www.pexels.com/photo/religious-figurines-with-heart-shaped-memorial-35967972/", "author_name": "Lara Derin Yalçın", "author_url": "https://www.pexels.com/@lara-derin-yalcin-2159169657", "license_name": "Pexels License", "license_url": "https://www.pexels.com/license/", "fallback_full_urls": []}, {"provider_id": "pexels", "thumbnail_url": "https://images.pexels.com/photos/8871419/pexels-photo-8871419.jpeg?auto=compress&cs=tinysrgb&h=350", "full_url": "https://images.pexels.com/photos/8871419/pexels-photo-8871419.jpeg?auto=compress&cs=tinysrgb&dpr=2&h=650&w=940", "extension": "jpg", "source_page_url": "https://www.pexels.com/photo/person-touching-photo-in-the-picture-frame-8871419/", "author_name": "Kampus Production", "author_url": "https://www.pexels.com/@kampus", "license_name": "Pexels License", "license_url": "https://www.pexels.com/license/", "fallback_full_urls": []}, {"provider_id": "pexels", "thumbnail_url": "https://images.pexels.com/photos/8871429/pexels-photo-8871429.jpeg?auto=compress&cs=tinysrgb&h=350", "full_url": "https://images.pexels.com/photos/8871429/pexels-photo-8871429.jpeg?auto=compress&cs=tinysrgb&dpr=2&h=650&w=940", "extension": "jpg", "source_page_url": "https://www.pexels.com/photo/person-holding-a-black-wooden-picture-frame-8871429/", "author_name": "Kampus Production", "author_url": "https://www.pexels.com/@kampus", "license_name": "Pexels License", "license_url": "https://www.pexels.com/license/", "fallback_full_urls": []}, {"provider_id": "pexels", "thumbnail_url": "https://images.pexels.com/photos/3831849/pexels-photo-3831849.jpeg?auto=compress&cs=tinysrgb&h=350", "full_url": "https://images.pexels.com/photos/3831849/pexels-photo-3831849.jpeg?auto=compress&cs=tinysrgb&dpr=2&h=650&w=940", "extension": "jpg", "source_page_url": "https://www.pexels.com/photo/colorful-sticky-notes-3831849/", "author_name": "cottonbro studio", "author_url": "https://www.pexels.com/@cottonbro", "license_name": "Pexels License", "license_url": "https://www.pexels.com/license/", "fallback_full_urls": []}, {"provider_id": "pexels", "thumbnail_url": "https://images.pexels.com/photos/4425982/pexels-photo-4425982.jpeg?auto=compress&cs=tinysrgb&h=350", "full_url": "https://images.pexels.com/photos/4425982/pexels-photo-4425982.jpeg?auto=compress&cs=tinysrgb&dpr=2&h=650&w=940", "extension": "jpg", "source_page_url": "https://www.pexels.com/photo/message-written-on-note-4425982/", "author_name": "Nothing Ahead", "author_url": "https://www.pexels.com/@ian-panelo", "license_name": "Pexels License", "license_url": "https://www.pexels.com/license/", "fallback_full_urls": []}, {"provider_id": "pexels", "thumbnail_url": "https://images.pexels.com/photos/34970927/pexels-photo-34970927.jpeg?auto=compress&cs=tinysrgb&h=350", "full_url": "https://images.pexels.com/photos/34970927/pexels-photo-34970927.jpeg?auto=compress&cs=tinysrgb&dpr=2&h=650&w=940", "extension": "jpg", "source_page_url": "https://www.pexels.com/photo/inspiring-sticky-note-on-vibrant-blue-background-34970927/", "author_name": "Christopher Welsch Leveroni", "author_url": "https://www.pexels.com/@christopher-welsch-leveroni-2150186467", "license_name": "Pexels License", "license_url": "https://www.pexels.com/license/", "fallback_full_urls": []}, {"provider_id": "pexels", "thumbnail_url": "https://images.pexels.com/photos/32010736/pexels-photo-32010736.jpeg?auto=compress&cs=tinysrgb&h=350", "full_url": "https://images.pexels.com/photos/32010736/pexels-photo-32010736.jpeg?auto=compress&cs=tinysrgb&dpr=2&h=650&w=940", "extension": "jpg", "source_page_url": "https://www.pexels.com/photo/hand-holding-cute-floral-card-outdoors-32010736/", "author_name": "Hiếu Lê", "author_url": "https://www.pexels.com/@hi-u-le-2151906536", "license_name": "Pexels License", "license_url": "https://www.pexels.com/license/", "fallback_full_urls": []}, {"provider_id": "pexels", "thumbnail_url": "https://images.pexels.com/photos/29546585/pexels-photo-29546585.jpeg?auto=compress&cs=tinysrgb&h=350", "full_url": "https://images.pexels.com/photos/29546585/pexels-photo-29546585.jpeg?auto=compress&cs=tinysrgb&dpr=2&h=650&w=940", "extension": "jpg", "source_page_url": "https://www.pexels.com/photo/motivational-post-it-note-on-blank-wall-29546585/", "author_name": "Airam Dato-on", "author_url": "https://www.pexels.com/@airamdphoto", "license_name": "Pexels License", "license_url": "https://www.pexels.com/license/", "fallback_full_urls": []}, {"provider_id": "pexels", "thumbnail_url": "https://images.pexels.com/photos/34777690/pexels-photo-34777690.jpeg?auto=compress&cs=tinysrgb&h=350", "full_url": "https://images.pexels.com/photos/34777690/pexels-photo-34777690.jpeg?auto=compress&cs=tinysrgb&dpr=2&h=650&w=940", "extension": "jpg", "source_page_url": "https://www.pexels.com/photo/close-up-of-red-poppies-in-bloom-with-hand-34777690/", "author_name": "Mehmet", "author_url": "https://www.pexels.com/@mehmet", "license_name": "Pexels License", "license_url": "https://www.pexels.com/license/", "fallback_full_urls": []}, {"provider_id": "pexels", "thumbnail_url": "https://images.pexels.com/photos/6230977/pexels-photo-6230977.jpeg?auto=compress&cs=tinysrgb&h=350", "full_url": "https://images.pexels.com/photos/6230977/pexels-photo-6230977.jpeg?auto=compress&cs=tinysrgb&dpr=2&h=650&w=940", "extension": "jpg", "source_page_url": "https://www.pexels.com/photo/close-up-shot-of-scrabble-tiles-on-a-white-surface-6230977/", "author_name": "Anna Tarazevich", "author_url": "https://www.pexels.com/@anntarazevich", "license_name": "Pexels License", "license_url": "https://www.pexels.com/license/", "fallback_full_urls": []}, {"provider_id": "pexels", "thumbnail_url": "https://images.pexels.com/photos/7857913/pexels-photo-7857913.jpeg?auto=compress&cs=tinysrgb&h=350", "full_url": "https://images.pexels.com/photos/7857913/pexels-photo-7857913.jpeg?auto=compress&cs=tinysrgb&dpr=2&h=650&w=940", "extension": "jpg", "source_page_url": "https://www.pexels.com/photo/calendar-and-a-text-saying-keep-calm-and-check-your-balls-on-light-background-7857913/", "author_name": "Leeloo The First", "author_url": "https://www.pexels.com/@leeloothefirst", "license_name": "Pexels License", "license_url": "https://www.pexels.com/license/", "fallback_full_urls": []}, {"provider_id": "pexels", "thumbnail_url": "https://images.pexels.com/photos/21070691/pexels-photo-21070691.jpeg?auto=compress&cs=tinysrgb&h=350", "full_url": "https://images.pexels.com/photos/21070691/pexels-photo-21070691.jpeg?auto=compress&cs=tinysrgb&dpr=2&h=650&w=940", "extension": "jpg", "source_page_url": "https://www.pexels.com/photo/magnets-on-wall-21070691/", "author_name": "Damir K .", "author_url": "https://www.pexels.com/@damir", "license_name": "Pexels License", "license_url": "https://www.pexels.com/license/", "fallback_full_urls": []}, {"provider_id": "pexels", "thumbnail_url": "https://images.pexels.com/photos/4099049/pexels-photo-4099049.jpeg?auto=compress&cs=tinysrgb&h=350", "full_url": "https://images.pexels.com/photos/4099049/pexels-photo-4099049.jpeg?auto=compress&cs=tinysrgb&dpr=2&h=650&w=940", "extension": "jpg", "source_page_url": "https://www.pexels.com/photo/close-up-shot-of-a-person-holding-an-orange-poppy-4099049/", "author_name": "Taryn Elliott", "author_url": "https://www.pexels.com/@taryn-elliott", "license_name": "Pexels License", "license_url": "https://www.pexels.com/license/", "fallback_full_urls": []}]}